{
  "symbol": "PEAQ",
  "trained_at": "2025-11-14T23:59:05.689905",
  "training_seed": 905549,
  "coin_model_seed": 905962,
  "rsi_params": {
    "oversold": 35,
    "overbought": 74,
    "exit_long_with_trend": 62,
    "exit_long_against_trend": 63,
    "exit_short_with_trend": 40,
    "exit_short_against_trend": 36
  },
  "risk_params": {
    "stop_loss": 17.502360556688295,
    "take_profit": 10.0,
    "trailing_stop_activation": 46.313263435612704,
    "trailing_stop_distance": 15.268930417227102,
    "break_even_protection": false,
    "break_even_trigger": 32.081277487840254,
    "max_position_hours": 13.0
  },
  "filter_params": {
    "rsi_time_filter": {
      "enabled": true,
      "candles": 3,
      "upper": 73.0,
      "lower": 37.0
    },
    "exit_scam_filter": {
      "enabled": true,
      "candles": 6,
      "single_candle_percent": 28.117787841508097,
      "multi_candle_count": 5,
      "multi_candle_percent": 64.4513165088604
    }
  },
  "candles_count": 1292,
  "trades_count": 5,
  "win_rate": 60.0,
  "signal_accuracy": 1.0,
  "profit_mse": 4.4179572872637335e-06,
  "total_pnl": 1.2455397955755083,
  "previous_candles_count": 1323,
  "candles_increased": false
}