{
  "symbol": "NS",
  "trained_at": "2025-11-13T16:40:09.814258",
  "training_seed": 195584,
  "coin_model_seed": 196531,
  "rsi_params": {
    "oversold": 35,
    "overbought": 72,
    "exit_long_with_trend": 67,
    "exit_long_against_trend": 63,
    "exit_short_with_trend": 34,
    "exit_short_against_trend": 36
  },
  "risk_params": {
    "stop_loss": 13.996612314718789,
    "take_profit": 25.048649255751922,
    "trailing_stop_activation": 14.119065740204665,
    "trailing_stop_distance": 6.924409991980724,
    "break_even_protection": false,
    "break_even_trigger": 155.69634824441454,
    "max_position_hours": 14
  },
  "filter_params": {
    "rsi_time_filter": {
      "enabled": true,
      "candles": 5,
      "upper": 61,
      "lower": 32
    },
    "exit_scam_filter": {
      "enabled": true,
      "candles": 10,
      "single_candle_percent": 15.059534614614666,
      "multi_candle_count": 2,
      "multi_candle_percent": 51.41855542964971
    }
  },
  "candles_count": 1309,
  "trades_count": 7,
  "win_rate": 71.42857142857143,
  "signal_accuracy": 1.0,
  "profit_mse": 3.4161592487399083e-06,
  "total_pnl": 0.6749544760751311,
  "previous_candles_count": 1116,
  "candles_increased": true
}