{
  "symbol": "HYPER",
  "timeframe": "1w",
  "candles": [
    {
      "time": 1745193600000,
      "open": 0.2409,
      "high": 0.3682,
      "low": 0.1835,
      "close": 0.1906,
      "volume": 951985959.0,
      "turnover": 232181044.7425
    },
    {
      "time": 1745798400000,
      "open": 0.1906,
      "high": 0.2047,
      "low": 0.1553,
      "close": 0.1617,
      "volume": 292058470.0,
      "turnover": 53597229.3497
    },
    {
      "time": 1746403200000,
      "open": 0.1617,
      "high": 0.1845,
      "low": 0.1327,
      "close": 0.1757,
      "volume": 320684237.0,
      "turnover": 50454425.8848
    },
    {
      "time": 1747008000000,
      "open": 0.1757,
      "high": 0.184,
      "low": 0.132,
      "close": 0.1448,
      "volume": 228877725.0,
      "turnover": 36418597.8825
    },
    {
      "time": 1747612800000,
      "open": 0.1448,
      "high": 0.1812,
      "low": 0.1325,
      "close": 0.1519,
      "volume": 254376807.0,
      "turnover": 39664415.8963
    },
    {
      "time": 1748217600000,
      "open": 0.1519,
      "high": 0.2091,
      "low": 0.1218,
      "close": 0.1373,
      "volume": 305497938.0,
      "turnover": 48347158.1698
    },
    {
      "time": 1748822400000,
      "open": 0.1373,
      "high": 0.1486,
      "low": 0.1172,
      "close": 0.1297,
      "volume": 100814839.0,
      "turnover": 13273326.8703
    },
    {
      "time": 1749427200000,
      "open": 0.1297,
      "high": 0.1428,
      "low": 0.1014,
      "close": 0.113,
      "volume": 118640035.0,
      "turnover": 14305271.7255
    },
    {
      "time": 1750032000000,
      "open": 0.113,
      "high": 0.1205,
      "low": 0.086,
      "close": 0.0925,
      "volume": 119668819.0,
      "turnover": 12551525.615
    },
    {
      "time": 1750636800000,
      "open": 0.0925,
      "high": 0.1081,
      "low": 0.0903,
      "close": 0.1064,
      "volume": 79769971.0,
      "turnover": 7832156.1613
    },
    {
      "time": 1751241600000,
      "open": 0.1064,
      "high": 0.1118,
      "low": 0.0972,
      "close": 0.1025,
      "volume": 57838461.0,
      "turnover": 6018955.0398
    },
    {
      "time": 1751846400000,
      "open": 0.1025,
      "high": 0.6735,
      "low": 0.1005,
      "close": 0.4381,
      "volume": 5889971534.0,
      "turnover": 2526849989.1875
    },
    {
      "time": 1752451200000,
      "open": 0.4381,
      "high": 0.4553,
      "low": 0.3378,
      "close": 0.3524,
      "volume": 853991387.0,
      "turnover": 336475728.0531
    },
    {
      "time": 1753056000000,
      "open": 0.3524,
      "high": 0.6211,
      "low": 0.3443,
      "close": 0.4601,
      "volume": 2279687621.0,
      "turnover": 1087485579.3693
    },
    {
      "time": 1753660800000,
      "open": 0.4601,
      "high": 0.5437,
      "low": 0.3719,
      "close": 0.3869,
      "volume": 1068787410.0,
      "turnover": 487256777.0222
    },
    {
      "time": 1754265600000,
      "open": 0.3869,
      "high": 0.4443,
      "low": 0.382,
      "close": 0.4195,
      "volume": 445325048.0,
      "turnover": 181987839.444
    },
    {
      "time": 1754870400000,
      "open": 0.4195,
      "high": 0.4391,
      "low": 0.3358,
      "close": 0.3603,
      "volume": 333017647.0,
      "turnover": 126184752.9559
    },
    {
      "time": 1755475200000,
      "open": 0.3603,
      "high": 0.3755,
      "low": 0.3027,
      "close": 0.3181,
      "volume": 364904519.0,
      "turnover": 122175456.6992
    },
    {
      "time": 1756080000000,
      "open": 0.3181,
      "high": 0.3516,
      "low": 0.2894,
      "close": 0.2997,
      "volume": 225991710.0,
      "turnover": 70628320.7165
    },
    {
      "time": 1756684800000,
      "open": 0.2997,
      "high": 0.3152,
      "low": 0.2791,
      "close": 0.3037,
      "volume": 88749259.0,
      "turnover": 26277291.4331
    },
    {
      "time": 1757289600000,
      "open": 0.3037,
      "high": 0.3477,
      "low": 0.3013,
      "close": 0.322,
      "volume": 120805028.0,
      "turnover": 39274143.2197
    },
    {
      "time": 1757894400000,
      "open": 0.322,
      "high": 0.3263,
      "low": 0.296,
      "close": 0.3162,
      "volume": 63248508.0,
      "turnover": 19489944.0205
    },
    {
      "time": 1758499200000,
      "open": 0.3162,
      "high": 0.3162,
      "low": 0.2449,
      "close": 0.2626,
      "volume": 146948393.0,
      "turnover": 39884980.7028
    },
    {
      "time": 1759104000000,
      "open": 0.2626,
      "high": 0.2979,
      "low": 0.2305,
      "close": 0.2648,
      "volume": 102919754.0,
      "turnover": 27104070.9223
    },
    {
      "time": 1759708800000,
      "open": 0.2648,
      "high": 0.3286,
      "low": 0.0755,
      "close": 0.2089,
      "volume": 207173495.0,
      "turnover": 47491103.8665
    },
    {
      "time": 1760313600000,
      "open": 0.2089,
      "high": 0.2368,
      "low": 0.178,
      "close": 0.2003,
      "volume": 188283475.0,
      "turnover": 39276854.3794
    },
    {
      "time": 1760918400000,
      "open": 0.2003,
      "high": 0.2104,
      "low": 0.178,
      "close": 0.2051,
      "volume": 82965825.0,
      "turnover": 16262206.8007
    },
    {
      "time": 1761523200000,
      "open": 0.2051,
      "high": 0.2076,
      "low": 0.1839,
      "close": 0.1864,
      "volume": 18353331.0,
      "turnover": 3563878.5138
    }
  ],
  "count": 28,
  "last_update": "2025-10-29T19:54:20.054999"
}