{
  "symbol": "DEXE",
  "timeframe": "1d",
  "candles": [
    {
      "time": 1721865600000,
      "open": 9.4,
      "high": 9.876,
      "low": 8.937,
      "close": 9.268,
      "volume": 313073.7,
      "turnover": 2961493.9328
    },
    {
      "time": 1721952000000,
      "open": 9.268,
      "high": 9.589,
      "low": 9.121,
      "close": 9.543,
      "volume": 74047.6,
      "turnover": 691661.0124
    },
    {
      "time": 1722038400000,
      "open": 9.543,
      "high": 9.692,
      "low": 9.261,
      "close": 9.42,
      "volume": 72457.5,
      "turnover": 688305.2859
    },
    {
      "time": 1722124800000,
      "open": 9.42,
      "high": 9.433,
      "low": 9.051,
      "close": 9.344,
      "volume": 49639.6,
      "turnover": 458879.7043
    },
    {
      "time": 1722211200000,
      "open": 9.344,
      "high": 10.051,
      "low": 9.309,
      "close": 9.717,
      "volume": 136147.5,
      "turnover": 1328728.4677
    },
    {
      "time": 1722297600000,
      "open": 9.717,
      "high": 9.991,
      "low": 9.282,
      "close": 9.355,
      "volume": 168926.7,
      "turnover": 1646149.3719
    },
    {
      "time": 1722384000000,
      "open": 9.355,
      "high": 9.496,
      "low": 8.95,
      "close": 8.976,
      "volume": 148020.7,
      "turnover": 1378665.9169
    },
    {
      "time": 1722470400000,
      "open": 8.976,
      "high": 9.072,
      "low": 8.363,
      "close": 8.813,
      "volume": 99827.6,
      "turnover": 867750.5023
    },
    {
      "time": 1722556800000,
      "open": 8.813,
      "high": 8.917,
      "low": 8.17,
      "close": 8.266,
      "volume": 89522.3,
      "turnover": 768836.0151
    },
    {
      "time": 1722643200000,
      "open": 8.266,
      "high": 8.542,
      "low": 7.701,
      "close": 7.845,
      "volume": 106824.6,
      "turnover": 866428.3597
    },
    {
      "time": 1722729600000,
      "open": 7.845,
      "high": 8.297,
      "low": 7.444,
      "close": 7.579,
      "volume": 128184.7,
      "turnover": 1022273.2596
    },
    {
      "time": 1722816000000,
      "open": 7.579,
      "high": 7.625,
      "low": 6.066,
      "close": 6.918,
      "volume": 151396.1,
      "turnover": 1011696.8894
    },
    {
      "time": 1722902400000,
      "open": 6.918,
      "high": 7.287,
      "low": 6.883,
      "close": 7.08,
      "volume": 170765.8,
      "turnover": 1215314.6806
    },
    {
      "time": 1722988800000,
      "open": 7.08,
      "high": 7.497,
      "low": 6.988,
      "close": 7.158,
      "volume": 69545.3,
      "turnover": 499348.1897
    },
    {
      "time": 1723075200000,
      "open": 7.158,
      "high": 8.116,
      "low": 7.104,
      "close": 7.772,
      "volume": 233442.7,
      "turnover": 1793873.3828
    },
    {
      "time": 1723161600000,
      "open": 7.772,
      "high": 7.828,
      "low": 7.519,
      "close": 7.824,
      "volume": 168046.5,
      "turnover": 1291565.7563
    },
    {
      "time": 1723248000000,
      "open": 7.824,
      "high": 7.877,
      "low": 7.624,
      "close": 7.692,
      "volume": 64960.1,
      "turnover": 501750.2894
    },
    {
      "time": 1723334400000,
      "open": 7.692,
      "high": 8.647,
      "low": 7.447,
      "close": 7.566,
      "volume": 189539.5,
      "turnover": 1500488.8065
    },
    {
      "time": 1723420800000,
      "open": 7.566,
      "high": 7.829,
      "low": 7.451,
      "close": 7.776,
      "volume": 57955.7,
      "turnover": 443734.0828
    },
    {
      "time": 1723507200000,
      "open": 7.776,
      "high": 7.789,
      "low": 7.42,
      "close": 7.706,
      "volume": 32203.1,
      "turnover": 245022.43
    },
    {
      "time": 1723593600000,
      "open": 7.706,
      "high": 7.866,
      "low": 7.534,
      "close": 7.556,
      "volume": 33943.4,
      "turnover": 260203.6789
    },
    {
      "time": 1723680000000,
      "open": 7.556,
      "high": 7.59,
      "low": 6.928,
      "close": 7.027,
      "volume": 68778.6,
      "turnover": 498002.4482
    },
    {
      "time": 1723766400000,
      "open": 7.027,
      "high": 7.185,
      "low": 6.874,
      "close": 7.091,
      "volume": 72869.2,
      "turnover": 514184.0182
    },
    {
      "time": 1723852800000,
      "open": 7.091,
      "high": 7.425,
      "low": 7.054,
      "close": 7.361,
      "volume": 34781.5,
      "turnover": 252173.7978
    },
    {
      "time": 1723939200000,
      "open": 7.361,
      "high": 7.966,
      "low": 7.256,
      "close": 7.729,
      "volume": 74689.4,
      "turnover": 571031.2722
    },
    {
      "time": 1724025600000,
      "open": 7.729,
      "high": 8.243,
      "low": 7.568,
      "close": 8.026,
      "volume": 92702.2,
      "turnover": 725710.7176
    },
    {
      "time": 1724112000000,
      "open": 8.026,
      "high": 8.147,
      "low": 7.81,
      "close": 8.075,
      "volume": 28066.6,
      "turnover": 225411.677
    },
    {
      "time": 1724198400000,
      "open": 8.075,
      "high": 8.532,
      "low": 7.988,
      "close": 8.457,
      "volume": 55261.6,
      "turnover": 452699.0527
    },
    {
      "time": 1724284800000,
      "open": 8.457,
      "high": 8.595,
      "low": 8.346,
      "close": 8.542,
      "volume": 29034.5,
      "turnover": 246536.7309
    },
    {
      "time": 1724371200000,
      "open": 8.542,
      "high": 9.129,
      "low": 8.51,
      "close": 9.1,
      "volume": 25749.3,
      "turnover": 226780.0653
    },
    {
      "time": 1724457600000,
      "open": 9.1,
      "high": 9.263,
      "low": 8.91,
      "close": 9.037,
      "volume": 25453.1,
      "turnover": 230774.1561
    },
    {
      "time": 1724544000000,
      "open": 9.037,
      "high": 9.119,
      "low": 8.74,
      "close": 8.864,
      "volume": 22731.2,
      "turnover": 202823.2007
    },
    {
      "time": 1724630400000,
      "open": 8.864,
      "high": 8.985,
      "low": 8.048,
      "close": 8.048,
      "volume": 27685.7,
      "turnover": 238360.4912
    },
    {
      "time": 1724716800000,
      "open": 8.048,
      "high": 8.305,
      "low": 7.63,
      "close": 7.684,
      "volume": 44882.0,
      "turnover": 361597.6361
    },
    {
      "time": 1724803200000,
      "open": 7.684,
      "high": 8.046,
      "low": 7.418,
      "close": 7.641,
      "volume": 93021.3,
      "turnover": 724511.6276
    },
    {
      "time": 1724889600000,
      "open": 7.641,
      "high": 7.977,
      "low": 7.57,
      "close": 7.612,
      "volume": 111999.9,
      "turnover": 870775.7023
    },
    {
      "time": 1724976000000,
      "open": 7.612,
      "high": 7.82,
      "low": 7.288,
      "close": 7.608,
      "volume": 39287.4,
      "turnover": 297447.6947
    },
    {
      "time": 1725062400000,
      "open": 7.608,
      "high": 7.648,
      "low": 7.167,
      "close": 7.292,
      "volume": 27587.4,
      "turnover": 204062.5863
    },
    {
      "time": 1725148800000,
      "open": 7.292,
      "high": 7.612,
      "low": 7.13,
      "close": 7.197,
      "volume": 37438.3,
      "turnover": 274577.047
    },
    {
      "time": 1725235200000,
      "open": 7.197,
      "high": 7.642,
      "low": 7.116,
      "close": 7.618,
      "volume": 24371.7,
      "turnover": 179286.3423
    },
    {
      "time": 1725321600000,
      "open": 7.618,
      "high": 7.839,
      "low": 7.332,
      "close": 7.336,
      "volume": 53898.4,
      "turnover": 412222.7722
    },
    {
      "time": 1725408000000,
      "open": 7.336,
      "high": 7.627,
      "low": 7.041,
      "close": 7.53,
      "volume": 27606.2,
      "turnover": 202724.4296
    },
    {
      "time": 1725494400000,
      "open": 7.53,
      "high": 7.557,
      "low": 7.227,
      "close": 7.267,
      "volume": 12643.4,
      "turnover": 93071.2705
    },
    {
      "time": 1725580800000,
      "open": 7.267,
      "high": 7.552,
      "low": 6.883,
      "close": 7.061,
      "volume": 24761.4,
      "turnover": 179910.7093
    },
    {
      "time": 1725667200000,
      "open": 7.061,
      "high": 7.375,
      "low": 7.008,
      "close": 7.039,
      "volume": 42860.4,
      "turnover": 310092.4328
    },
    {
      "time": 1725753600000,
      "open": 7.039,
      "high": 7.426,
      "low": 6.958,
      "close": 7.413,
      "volume": 45064.6,
      "turnover": 326520.4683
    },
    {
      "time": 1725840000000,
      "open": 7.413,
      "high": 8.349,
      "low": 7.38,
      "close": 7.725,
      "volume": 82104.7,
      "turnover": 636313.1387
    },
    {
      "time": 1725926400000,
      "open": 7.725,
      "high": 7.922,
      "low": 7.611,
      "close": 7.853,
      "volume": 28742.1,
      "turnover": 224460.9344
    },
    {
      "time": 1726012800000,
      "open": 7.853,
      "high": 7.876,
      "low": 7.566,
      "close": 7.809,
      "volume": 23130.1,
      "turnover": 178892.1801
    },
    {
      "time": 1726099200000,
      "open": 7.809,
      "high": 8.021,
      "low": 7.767,
      "close": 7.98,
      "volume": 27403.6,
      "turnover": 216484.2363
    },
    {
      "time": 1726185600000,
      "open": 7.98,
      "high": 8.088,
      "low": 7.849,
      "close": 8.081,
      "volume": 36216.7,
      "turnover": 288174.2798
    },
    {
      "time": 1726272000000,
      "open": 8.081,
      "high": 8.16,
      "low": 7.978,
      "close": 8.052,
      "volume": 25773.5,
      "turnover": 207547.003
    },
    {
      "time": 1726358400000,
      "open": 8.052,
      "high": 8.13,
      "low": 7.654,
      "close": 7.657,
      "volume": 15962.7,
      "turnover": 127457.5871
    },
    {
      "time": 1726444800000,
      "open": 7.657,
      "high": 7.657,
      "low": 7.243,
      "close": 7.317,
      "volume": 16219.3,
      "turnover": 120419.5472
    },
    {
      "time": 1726531200000,
      "open": 7.317,
      "high": 7.737,
      "low": 7.312,
      "close": 7.658,
      "volume": 18024.9,
      "turnover": 136314.714
    },
    {
      "time": 1726617600000,
      "open": 7.658,
      "high": 7.91,
      "low": 7.414,
      "close": 7.907,
      "volume": 19942.8,
      "turnover": 152105.3285
    },
    {
      "time": 1726704000000,
      "open": 7.907,
      "high": 8.566,
      "low": 7.907,
      "close": 8.377,
      "volume": 17269.5,
      "turnover": 142722.8645
    },
    {
      "time": 1726790400000,
      "open": 8.377,
      "high": 8.753,
      "low": 8.292,
      "close": 8.723,
      "volume": 13211.4,
      "turnover": 113664.1897
    },
    {
      "time": 1726876800000,
      "open": 8.723,
      "high": 8.889,
      "low": 8.624,
      "close": 8.866,
      "volume": 17913.7,
      "turnover": 156305.12
    },
    {
      "time": 1726963200000,
      "open": 8.866,
      "high": 8.902,
      "low": 8.42,
      "close": 8.684,
      "volume": 40888.1,
      "turnover": 353400.3844
    },
    {
      "time": 1727049600000,
      "open": 8.684,
      "high": 8.9,
      "low": 8.602,
      "close": 8.881,
      "volume": 19813.6,
      "turnover": 175085.0826
    },
    {
      "time": 1727136000000,
      "open": 8.881,
      "high": 9.032,
      "low": 8.657,
      "close": 8.94,
      "volume": 21146.8,
      "turnover": 186764.0444
    },
    {
      "time": 1727222400000,
      "open": 8.94,
      "high": 8.948,
      "low": 8.669,
      "close": 8.669,
      "volume": 9985.7,
      "turnover": 88152.9841
    },
    {
      "time": 1727308800000,
      "open": 8.669,
      "high": 8.948,
      "low": 8.552,
      "close": 8.827,
      "volume": 15033.3,
      "turnover": 132444.8401
    },
    {
      "time": 1727395200000,
      "open": 8.827,
      "high": 9.403,
      "low": 8.799,
      "close": 9.128,
      "volume": 28261.2,
      "turnover": 256447.6427
    },
    {
      "time": 1727481600000,
      "open": 9.128,
      "high": 9.357,
      "low": 8.707,
      "close": 8.796,
      "volume": 9711.8,
      "turnover": 86704.9256
    },
    {
      "time": 1727568000000,
      "open": 8.796,
      "high": 9.112,
      "low": 8.691,
      "close": 9.016,
      "volume": 18269.1,
      "turnover": 163700.8068
    },
    {
      "time": 1727654400000,
      "open": 9.016,
      "high": 9.033,
      "low": 8.375,
      "close": 8.463,
      "volume": 18545.1,
      "turnover": 159618.2075
    },
    {
      "time": 1727740800000,
      "open": 8.463,
      "high": 8.792,
      "low": 7.655,
      "close": 7.71,
      "volume": 48777.2,
      "turnover": 397263.9071
    },
    {
      "time": 1727827200000,
      "open": 7.71,
      "high": 7.935,
      "low": 7.455,
      "close": 7.533,
      "volume": 32174.6,
      "turnover": 249229.9712
    },
    {
      "time": 1727913600000,
      "open": 7.533,
      "high": 7.948,
      "low": 7.316,
      "close": 7.517,
      "volume": 42841.9,
      "turnover": 325423.81
    },
    {
      "time": 1728000000000,
      "open": 7.517,
      "high": 7.787,
      "low": 7.502,
      "close": 7.703,
      "volume": 35686.0,
      "turnover": 273620.5976
    },
    {
      "time": 1728086400000,
      "open": 7.703,
      "high": 7.924,
      "low": 7.613,
      "close": 7.772,
      "volume": 25119.1,
      "turnover": 194339.2489
    },
    {
      "time": 1728172800000,
      "open": 7.772,
      "high": 8.283,
      "low": 7.718,
      "close": 8.271,
      "volume": 46800.4,
      "turnover": 372210.1364
    },
    {
      "time": 1728259200000,
      "open": 8.271,
      "high": 8.491,
      "low": 8.156,
      "close": 8.246,
      "volume": 44501.7,
      "turnover": 371797.3497
    },
    {
      "time": 1728345600000,
      "open": 8.246,
      "high": 8.458,
      "low": 8.099,
      "close": 8.132,
      "volume": 42123.0,
      "turnover": 346956.3807
    },
    {
      "time": 1728432000000,
      "open": 8.132,
      "high": 8.292,
      "low": 7.832,
      "close": 7.953,
      "volume": 19484.4,
      "turnover": 157720.1689
    },
    {
      "time": 1728518400000,
      "open": 7.953,
      "high": 8.113,
      "low": 7.765,
      "close": 7.985,
      "volume": 15153.9,
      "turnover": 120448.3931
    },
    {
      "time": 1728604800000,
      "open": 7.985,
      "high": 8.448,
      "low": 7.968,
      "close": 8.359,
      "volume": 11147.1,
      "turnover": 91790.4309
    },
    {
      "time": 1728691200000,
      "open": 8.359,
      "high": 8.63,
      "low": 8.329,
      "close": 8.5,
      "volume": 20468.1,
      "turnover": 173543.1926
    },
    {
      "time": 1728777600000,
      "open": 8.5,
      "high": 8.654,
      "low": 8.268,
      "close": 8.641,
      "volume": 23125.3,
      "turnover": 195363.1188
    },
    {
      "time": 1728864000000,
      "open": 8.641,
      "high": 8.921,
      "low": 8.502,
      "close": 8.858,
      "volume": 16295.4,
      "turnover": 142340.7102
    },
    {
      "time": 1728950400000,
      "open": 8.858,
      "high": 8.999,
      "low": 8.488,
      "close": 8.735,
      "volume": 20870.1,
      "turnover": 183108.2618
    },
    {
      "time": 1729036800000,
      "open": 8.735,
      "high": 8.776,
      "low": 8.533,
      "close": 8.647,
      "volume": 17644.5,
      "turnover": 152927.9499
    },
    {
      "time": 1729123200000,
      "open": 8.647,
      "high": 8.73,
      "low": 8.284,
      "close": 8.418,
      "volume": 14769.8,
      "turnover": 125509.8545
    },
    {
      "time": 1729209600000,
      "open": 8.418,
      "high": 8.539,
      "low": 8.337,
      "close": 8.472,
      "volume": 15293.3,
      "turnover": 129460.2175
    },
    {
      "time": 1729296000000,
      "open": 8.472,
      "high": 8.614,
      "low": 8.403,
      "close": 8.519,
      "volume": 14052.0,
      "turnover": 119415.1827
    },
    {
      "time": 1729382400000,
      "open": 8.519,
      "high": 8.87,
      "low": 8.459,
      "close": 8.867,
      "volume": 15201.2,
      "turnover": 132491.882
    },
    {
      "time": 1729468800000,
      "open": 8.867,
      "high": 8.994,
      "low": 8.598,
      "close": 8.67,
      "volume": 21957.7,
      "turnover": 192223.0645
    },
    {
      "time": 1729555200000,
      "open": 8.67,
      "high": 8.737,
      "low": 8.479,
      "close": 8.666,
      "volume": 15365.2,
      "turnover": 132211.1662
    },
    {
      "time": 1729641600000,
      "open": 8.666,
      "high": 8.673,
      "low": 8.202,
      "close": 8.232,
      "volume": 8827.2,
      "turnover": 74118.627
    },
    {
      "time": 1729728000000,
      "open": 8.232,
      "high": 8.436,
      "low": 8.134,
      "close": 8.388,
      "volume": 13140.1,
      "turnover": 109270.0465
    },
    {
      "time": 1729814400000,
      "open": 8.388,
      "high": 8.493,
      "low": 7.827,
      "close": 7.909,
      "volume": 25458.9,
      "turnover": 205841.0846
    },
    {
      "time": 1729900800000,
      "open": 7.909,
      "high": 7.945,
      "low": 7.751,
      "close": 7.881,
      "volume": 8805.1,
      "turnover": 69139.2635
    },
    {
      "time": 1729987200000,
      "open": 7.881,
      "high": 7.974,
      "low": 7.754,
      "close": 7.932,
      "volume": 14062.8,
      "turnover": 110849.9242
    },
    {
      "time": 1730073600000,
      "open": 7.932,
      "high": 8.083,
      "low": 7.676,
      "close": 8.066,
      "volume": 17252.8,
      "turnover": 134767.552
    },
    {
      "time": 1730160000000,
      "open": 8.066,
      "high": 8.56,
      "low": 8.063,
      "close": 8.448,
      "volume": 20790.7,
      "turnover": 174715.2653
    },
    {
      "time": 1730246400000,
      "open": 8.448,
      "high": 8.567,
      "low": 8.354,
      "close": 8.412,
      "volume": 18254.3,
      "turnover": 154826.4727
    },
    {
      "time": 1730332800000,
      "open": 8.412,
      "high": 8.423,
      "low": 7.923,
      "close": 7.948,
      "volume": 13579.5,
      "turnover": 111897.7797
    },
    {
      "time": 1730419200000,
      "open": 7.948,
      "high": 8.112,
      "low": 7.742,
      "close": 7.88,
      "volume": 19292.6,
      "turnover": 151851.2153
    },
    {
      "time": 1730505600000,
      "open": 7.88,
      "high": 7.9,
      "low": 7.602,
      "close": 7.613,
      "volume": 4025.7,
      "turnover": 31242.4587
    },
    {
      "time": 1730592000000,
      "open": 7.613,
      "high": 7.627,
      "low": 7.169,
      "close": 7.355,
      "volume": 11770.7,
      "turnover": 86977.2143
    },
    {
      "time": 1730678400000,
      "open": 7.355,
      "high": 7.521,
      "low": 7.139,
      "close": 7.239,
      "volume": 15792.1,
      "turnover": 116421.2004
    },
    {
      "time": 1730764800000,
      "open": 7.239,
      "high": 7.774,
      "low": 7.239,
      "close": 7.561,
      "volume": 17801.2,
      "turnover": 134042.0819
    },
    {
      "time": 1730851200000,
      "open": 7.561,
      "high": 8.322,
      "low": 7.555,
      "close": 8.317,
      "volume": 36329.8,
      "turnover": 289512.362
    },
    {
      "time": 1730937600000,
      "open": 8.317,
      "high": 8.476,
      "low": 8.216,
      "close": 8.429,
      "volume": 24338.5,
      "turnover": 203166.4026
    },
    {
      "time": 1731024000000,
      "open": 8.429,
      "high": 8.568,
      "low": 8.289,
      "close": 8.465,
      "volume": 21849.8,
      "turnover": 183615.7263
    },
    {
      "time": 1731110400000,
      "open": 8.465,
      "high": 8.76,
      "low": 8.378,
      "close": 8.741,
      "volume": 18145.7,
      "turnover": 156606.1699
    },
    {
      "time": 1731196800000,
      "open": 8.741,
      "high": 9.131,
      "low": 8.475,
      "close": 8.826,
      "volume": 24063.1,
      "turnover": 213894.4061
    },
    {
      "time": 1731283200000,
      "open": 8.826,
      "high": 10.485,
      "low": 8.696,
      "close": 9.83,
      "volume": 172909.0,
      "turnover": 1672806.509
    },
    {
      "time": 1731369600000,
      "open": 9.83,
      "high": 9.831,
      "low": 8.811,
      "close": 9.253,
      "volume": 127988.5,
      "turnover": 1184270.6576
    },
    {
      "time": 1731456000000,
      "open": 9.253,
      "high": 9.383,
      "low": 8.447,
      "close": 8.678,
      "volume": 86554.4,
      "turnover": 753196.7752
    },
    {
      "time": 1731542400000,
      "open": 8.678,
      "high": 8.84,
      "low": 8.424,
      "close": 8.634,
      "volume": 69349.7,
      "turnover": 598898.3736
    },
    {
      "time": 1731628800000,
      "open": 8.634,
      "high": 8.91,
      "low": 8.452,
      "close": 8.873,
      "volume": 55691.3,
      "turnover": 484332.7809
    },
    {
      "time": 1731715200000,
      "open": 8.873,
      "high": 9.315,
      "low": 8.827,
      "close": 9.258,
      "volume": 50936.0,
      "turnover": 462693.6112
    },
    {
      "time": 1731801600000,
      "open": 9.258,
      "high": 9.759,
      "low": 8.823,
      "close": 8.994,
      "volume": 97695.9,
      "turnover": 897672.2402
    },
    {
      "time": 1731888000000,
      "open": 8.994,
      "high": 9.522,
      "low": 8.945,
      "close": 9.503,
      "volume": 81282.3,
      "turnover": 751744.8411
    },
    {
      "time": 1731974400000,
      "open": 9.503,
      "high": 9.529,
      "low": 9.222,
      "close": 9.425,
      "volume": 54692.4,
      "turnover": 513475.9048
    },
    {
      "time": 1732060800000,
      "open": 9.425,
      "high": 9.425,
      "low": 8.421,
      "close": 8.457,
      "volume": 81912.0,
      "turnover": 725274.8453
    },
    {
      "time": 1732147200000,
      "open": 8.457,
      "high": 8.679,
      "low": 8.241,
      "close": 8.567,
      "volume": 119178.5,
      "turnover": 1008660.9564
    },
    {
      "time": 1732233600000,
      "open": 8.567,
      "high": 8.68,
      "low": 8.176,
      "close": 8.468,
      "volume": 78988.5,
      "turnover": 662746.4296
    },
    {
      "time": 1732320000000,
      "open": 8.468,
      "high": 8.948,
      "low": 8.211,
      "close": 8.457,
      "volume": 62279.4,
      "turnover": 531418.6358
    },
    {
      "time": 1732406400000,
      "open": 8.457,
      "high": 8.886,
      "low": 7.969,
      "close": 8.586,
      "volume": 84017.0,
      "turnover": 710833.1105
    },
    {
      "time": 1732492800000,
      "open": 8.586,
      "high": 8.806,
      "low": 8.093,
      "close": 8.261,
      "volume": 149221.1,
      "turnover": 1254084.5052
    },
    {
      "time": 1732579200000,
      "open": 8.261,
      "high": 8.553,
      "low": 7.896,
      "close": 8.048,
      "volume": 182933.7,
      "turnover": 1496053.644
    },
    {
      "time": 1732665600000,
      "open": 8.048,
      "high": 8.583,
      "low": 7.958,
      "close": 8.582,
      "volume": 156314.6,
      "turnover": 1293368.4976
    },
    {
      "time": 1732752000000,
      "open": 8.582,
      "high": 8.771,
      "low": 8.283,
      "close": 8.669,
      "volume": 122602.5,
      "turnover": 1040305.8291
    },
    {
      "time": 1732838400000,
      "open": 8.669,
      "high": 9.0,
      "low": 8.548,
      "close": 8.983,
      "volume": 57170.0,
      "turnover": 502693.6453
    },
    {
      "time": 1732924800000,
      "open": 8.983,
      "high": 9.306,
      "low": 8.845,
      "close": 9.188,
      "volume": 109689.5,
      "turnover": 995173.0265
    },
    {
      "time": 1733011200000,
      "open": 9.188,
      "high": 9.636,
      "low": 8.855,
      "close": 9.487,
      "volume": 90968.1,
      "turnover": 834900.5767
    },
    {
      "time": 1733097600000,
      "open": 9.487,
      "high": 10.042,
      "low": 8.745,
      "close": 9.953,
      "volume": 145298.2,
      "turnover": 1362041.5042
    },
    {
      "time": 1733184000000,
      "open": 9.953,
      "high": 10.651,
      "low": 9.611,
      "close": 10.621,
      "volume": 130059.3,
      "turnover": 1316315.0168
    },
    {
      "time": 1733270400000,
      "open": 10.621,
      "high": 11.272,
      "low": 10.3,
      "close": 10.852,
      "volume": 62992.5,
      "turnover": 685179.7317
    },
    {
      "time": 1733356800000,
      "open": 10.852,
      "high": 10.97,
      "low": 10.217,
      "close": 10.595,
      "volume": 65581.1,
      "turnover": 698924.1799
    },
    {
      "time": 1733443200000,
      "open": 10.595,
      "high": 11.34,
      "low": 10.428,
      "close": 11.016,
      "volume": 70370.6,
      "turnover": 768265.9209
    },
    {
      "time": 1733529600000,
      "open": 11.016,
      "high": 11.192,
      "low": 10.852,
      "close": 10.929,
      "volume": 26243.3,
      "turnover": 289935.8141
    },
    {
      "time": 1733616000000,
      "open": 10.929,
      "high": 11.516,
      "low": 10.678,
      "close": 11.342,
      "volume": 65686.7,
      "turnover": 727488.2741
    },
    {
      "time": 1733702400000,
      "open": 11.342,
      "high": 11.414,
      "low": 8.829,
      "close": 9.68,
      "volume": 116947.7,
      "turnover": 1184039.681
    },
    {
      "time": 1733788800000,
      "open": 9.68,
      "high": 9.932,
      "low": 8.926,
      "close": 9.539,
      "volume": 175488.4,
      "turnover": 1662235.6679
    },
    {
      "time": 1733875200000,
      "open": 9.539,
      "high": 10.885,
      "low": 9.187,
      "close": 9.554,
      "volume": 331017.2,
      "turnover": 3257594.5222
    },
    {
      "time": 1733961600000,
      "open": 9.554,
      "high": 10.067,
      "low": 9.312,
      "close": 9.869,
      "volume": 118176.2,
      "turnover": 1152039.401
    },
    {
      "time": 1734048000000,
      "open": 9.869,
      "high": 10.142,
      "low": 9.427,
      "close": 10.092,
      "volume": 61721.1,
      "turnover": 603844.3005
    },
    {
      "time": 1734134400000,
      "open": 10.092,
      "high": 10.207,
      "low": 9.382,
      "close": 9.56,
      "volume": 46501.8,
      "turnover": 457777.7896
    },
    {
      "time": 1734220800000,
      "open": 9.56,
      "high": 10.099,
      "low": 8.224,
      "close": 8.592,
      "volume": 136685.6,
      "turnover": 1222411.1913
    },
    {
      "time": 1734307200000,
      "open": 8.592,
      "high": 8.918,
      "low": 7.34,
      "close": 7.379,
      "volume": 154933.8,
      "turnover": 1288770.5731
    },
    {
      "time": 1734393600000,
      "open": 7.379,
      "high": 9.282,
      "low": 7.346,
      "close": 8.079,
      "volume": 596420.0,
      "turnover": 4961727.3088
    },
    {
      "time": 1734480000000,
      "open": 8.079,
      "high": 8.451,
      "low": 7.523,
      "close": 7.537,
      "volume": 148838.0,
      "turnover": 1207691.3077
    },
    {
      "time": 1734566400000,
      "open": 7.537,
      "high": 8.717,
      "low": 7.516,
      "close": 8.368,
      "volume": 277037.5,
      "turnover": 2278079.2794
    },
    {
      "time": 1734652800000,
      "open": 8.368,
      "high": 10.35,
      "low": 7.702,
      "close": 9.129,
      "volume": 1525824.0,
      "turnover": 14527943.7239
    },
    {
      "time": 1734739200000,
      "open": 9.129,
      "high": 10.549,
      "low": 8.473,
      "close": 9.655,
      "volume": 666522.2,
      "turnover": 6153075.0818
    },
    {
      "time": 1734825600000,
      "open": 9.655,
      "high": 11.146,
      "low": 8.853,
      "close": 10.121,
      "volume": 1408876.3,
      "turnover": 14458533.8705
    },
    {
      "time": 1734912000000,
      "open": 10.121,
      "high": 13.385,
      "low": 9.86,
      "close": 12.998,
      "volume": 2689753.8,
      "turnover": 32033052.0396
    },
    {
      "time": 1734998400000,
      "open": 12.998,
      "high": 15.492,
      "low": 11.938,
      "close": 14.702,
      "volume": 2443376.6,
      "turnover": 32669658.7025
    },
    {
      "time": 1735084800000,
      "open": 14.702,
      "high": 15.82,
      "low": 12.905,
      "close": 13.431,
      "volume": 611273.8,
      "turnover": 8566036.9145
    },
    {
      "time": 1735171200000,
      "open": 13.431,
      "high": 13.956,
      "low": 12.646,
      "close": 13.377,
      "volume": 358505.3,
      "turnover": 4760307.2579
    },
    {
      "time": 1735257600000,
      "open": 13.377,
      "high": 13.392,
      "low": 11.021,
      "close": 12.205,
      "volume": 1005499.1,
      "turnover": 12050264.4136
    },
    {
      "time": 1735344000000,
      "open": 12.205,
      "high": 13.947,
      "low": 12.03,
      "close": 12.911,
      "volume": 1097596.2,
      "turnover": 14297884.9733
    },
    {
      "time": 1735430400000,
      "open": 12.911,
      "high": 14.256,
      "low": 12.472,
      "close": 12.476,
      "volume": 445742.1,
      "turnover": 5974686.4771
    },
    {
      "time": 1735516800000,
      "open": 12.476,
      "high": 15.926,
      "low": 12.447,
      "close": 14.314,
      "volume": 864849.8,
      "turnover": 12268946.4327
    },
    {
      "time": 1735603200000,
      "open": 14.314,
      "high": 15.364,
      "low": 13.717,
      "close": 14.931,
      "volume": 1246401.6,
      "turnover": 18263705.7923
    },
    {
      "time": 1735689600000,
      "open": 14.931,
      "high": 15.739,
      "low": 14.597,
      "close": 14.963,
      "volume": 767221.5,
      "turnover": 11648218.8618
    },
    {
      "time": 1735776000000,
      "open": 14.963,
      "high": 21.863,
      "low": 14.816,
      "close": 19.772,
      "volume": 2816208.9,
      "turnover": 54221114.4403
    },
    {
      "time": 1735862400000,
      "open": 19.772,
      "high": 20.093,
      "low": 18.319,
      "close": 18.618,
      "volume": 1414857.6,
      "turnover": 27131914.133
    },
    {
      "time": 1735948800000,
      "open": 18.618,
      "high": 19.778,
      "low": 16.915,
      "close": 17.197,
      "volume": 941981.7,
      "turnover": 16934182.014
    },
    {
      "time": 1736035200000,
      "open": 17.197,
      "high": 17.486,
      "low": 16.788,
      "close": 16.984,
      "volume": 417931.8,
      "turnover": 7188601.3043
    },
    {
      "time": 1736121600000,
      "open": 16.984,
      "high": 17.251,
      "low": 15.832,
      "close": 16.14,
      "volume": 589489.2,
      "turnover": 9710096.5537
    },
    {
      "time": 1736208000000,
      "open": 16.14,
      "high": 16.437,
      "low": 15.308,
      "close": 15.36,
      "volume": 595459.0,
      "turnover": 9422487.3356
    },
    {
      "time": 1736294400000,
      "open": 15.36,
      "high": 16.197,
      "low": 14.266,
      "close": 14.927,
      "volume": 763523.6,
      "turnover": 11791082.8734
    },
    {
      "time": 1736380800000,
      "open": 14.927,
      "high": 15.384,
      "low": 14.03,
      "close": 14.716,
      "volume": 521166.3,
      "turnover": 7633073.5641
    },
    {
      "time": 1736467200000,
      "open": 14.716,
      "high": 15.37,
      "low": 14.24,
      "close": 14.999,
      "volume": 364356.8,
      "turnover": 5418423.713
    },
    {
      "time": 1736553600000,
      "open": 14.999,
      "high": 16.471,
      "low": 14.751,
      "close": 15.981,
      "volume": 799988.1,
      "turnover": 12660608.1953
    },
    {
      "time": 1736640000000,
      "open": 15.981,
      "high": 16.708,
      "low": 15.608,
      "close": 16.126,
      "volume": 457665.7,
      "turnover": 7366900.0748
    },
    {
      "time": 1736726400000,
      "open": 16.126,
      "high": 16.288,
      "low": 13.366,
      "close": 13.641,
      "volume": 563577.9,
      "turnover": 8210499.2173
    },
    {
      "time": 1736812800000,
      "open": 13.641,
      "high": 17.34,
      "low": 13.27,
      "close": 16.808,
      "volume": 992589.2,
      "turnover": 15043201.7473
    },
    {
      "time": 1736899200000,
      "open": 16.808,
      "high": 19.312,
      "low": 15.778,
      "close": 17.858,
      "volume": 881516.7,
      "turnover": 14871545.4486
    },
    {
      "time": 1736985600000,
      "open": 17.858,
      "high": 17.956,
      "low": 16.206,
      "close": 16.425,
      "volume": 384239.3,
      "turnover": 6517211.6495
    },
    {
      "time": 1737072000000,
      "open": 16.425,
      "high": 17.907,
      "low": 16.425,
      "close": 16.935,
      "volume": 365310.0,
      "turnover": 6314250.3741
    },
    {
      "time": 1737158400000,
      "open": 16.935,
      "high": 17.681,
      "low": 16.297,
      "close": 17.493,
      "volume": 527742.2,
      "turnover": 9012887.017
    },
    {
      "time": 1737244800000,
      "open": 17.493,
      "high": 18.593,
      "low": 16.505,
      "close": 17.623,
      "volume": 665113.4,
      "turnover": 11608900.6589
    },
    {
      "time": 1737331200000,
      "open": 17.623,
      "high": 19.826,
      "low": 17.323,
      "close": 18.82,
      "volume": 875200.4,
      "turnover": 16071474.4032
    },
    {
      "time": 1737417600000,
      "open": 18.82,
      "high": 20.483,
      "low": 18.071,
      "close": 19.653,
      "volume": 276136.9,
      "turnover": 5243063.6212
    },
    {
      "time": 1737504000000,
      "open": 19.653,
      "high": 21.38,
      "low": 19.167,
      "close": 19.612,
      "volume": 263532.5,
      "turnover": 5360645.0927
    },
    {
      "time": 1737590400000,
      "open": 19.612,
      "high": 19.76,
      "low": 18.569,
      "close": 19.351,
      "volume": 256013.2,
      "turnover": 4888722.8212
    },
    {
      "time": 1737676800000,
      "open": 19.351,
      "high": 20.152,
      "low": 18.466,
      "close": 18.59,
      "volume": 220844.6,
      "turnover": 4214273.1441
    },
    {
      "time": 1737763200000,
      "open": 18.59,
      "high": 20.174,
      "low": 18.467,
      "close": 19.598,
      "volume": 262769.4,
      "turnover": 5119638.1893
    },
    {
      "time": 1737849600000,
      "open": 19.598,
      "high": 20.618,
      "low": 19.406,
      "close": 19.624,
      "volume": 160233.3,
      "turnover": 3212529.6732
    },
    {
      "time": 1737936000000,
      "open": 19.624,
      "high": 21.756,
      "low": 19.08,
      "close": 21.449,
      "volume": 452805.1,
      "turnover": 9310276.7963
    },
    {
      "time": 1738022400000,
      "open": 21.449,
      "high": 21.911,
      "low": 19.001,
      "close": 19.425,
      "volume": 215763.2,
      "turnover": 4427905.1629
    },
    {
      "time": 1738108800000,
      "open": 19.425,
      "high": 19.949,
      "low": 13.48,
      "close": 16.197,
      "volume": 2445419.5,
      "turnover": 37814557.6403
    },
    {
      "time": 1738195200000,
      "open": 16.197,
      "high": 21.555,
      "low": 15.725,
      "close": 21.045,
      "volume": 1452882.3,
      "turnover": 27047166.8921
    },
    {
      "time": 1738281600000,
      "open": 21.045,
      "high": 22.052,
      "low": 20.31,
      "close": 21.494,
      "volume": 1390689.4,
      "turnover": 29171296.4215
    },
    {
      "time": 1738368000000,
      "open": 21.494,
      "high": 22.392,
      "low": 20.632,
      "close": 21.03,
      "volume": 596661.9,
      "turnover": 12760944.4787
    },
    {
      "time": 1738454400000,
      "open": 21.03,
      "high": 21.84,
      "low": 19.611,
      "close": 20.254,
      "volume": 579349.2,
      "turnover": 12067798.0456
    },
    {
      "time": 1738540800000,
      "open": 20.254,
      "high": 24.2,
      "low": 19.415,
      "close": 23.984,
      "volume": 1018612.5,
      "turnover": 22546238.4677
    },
    {
      "time": 1738627200000,
      "open": 23.984,
      "high": 24.115,
      "low": 20.72,
      "close": 21.025,
      "volume": 470517.3,
      "turnover": 10350048.4801
    },
    {
      "time": 1738713600000,
      "open": 21.025,
      "high": 22.141,
      "low": 20.479,
      "close": 20.77,
      "volume": 278170.4,
      "turnover": 5924284.3807
    },
    {
      "time": 1738800000000,
      "open": 20.77,
      "high": 21.498,
      "low": 19.798,
      "close": 20.188,
      "volume": 258114.0,
      "turnover": 5329137.6515
    },
    {
      "time": 1738886400000,
      "open": 20.188,
      "high": 21.103,
      "low": 19.572,
      "close": 20.634,
      "volume": 251304.3,
      "turnover": 5101194.1734
    },
    {
      "time": 1738972800000,
      "open": 20.634,
      "high": 21.012,
      "low": 19.705,
      "close": 20.087,
      "volume": 141185.7,
      "turnover": 2862011.6608
    },
    {
      "time": 1739059200000,
      "open": 20.087,
      "high": 22.803,
      "low": 18.771,
      "close": 19.566,
      "volume": 673482.7,
      "turnover": 13795641.2362
    },
    {
      "time": 1739145600000,
      "open": 19.566,
      "high": 19.844,
      "low": 18.782,
      "close": 19.404,
      "volume": 217237.0,
      "turnover": 4179780.6655
    },
    {
      "time": 1739232000000,
      "open": 19.404,
      "high": 19.696,
      "low": 18.738,
      "close": 19.084,
      "volume": 208826.6,
      "turnover": 4012675.4363
    },
    {
      "time": 1739318400000,
      "open": 19.084,
      "high": 19.172,
      "low": 17.705,
      "close": 18.66,
      "volume": 181539.3,
      "turnover": 3335339.9462
    },
    {
      "time": 1739404800000,
      "open": 18.66,
      "high": 18.731,
      "low": 17.343,
      "close": 17.663,
      "volume": 136070.9,
      "turnover": 2427043.069
    },
    {
      "time": 1739491200000,
      "open": 17.663,
      "high": 18.54,
      "low": 17.586,
      "close": 18.122,
      "volume": 99950.0,
      "turnover": 1807826.6025
    },
    {
      "time": 1739577600000,
      "open": 18.122,
      "high": 18.468,
      "low": 17.581,
      "close": 17.815,
      "volume": 94837.1,
      "turnover": 1713153.4272
    },
    {
      "time": 1739664000000,
      "open": 17.815,
      "high": 17.915,
      "low": 17.024,
      "close": 17.448,
      "volume": 195631.7,
      "turnover": 3394101.0045
    },
    {
      "time": 1739750400000,
      "open": 17.448,
      "high": 18.21,
      "low": 17.325,
      "close": 18.043,
      "volume": 84440.4,
      "turnover": 1501989.7653
    },
    {
      "time": 1739836800000,
      "open": 18.043,
      "high": 18.392,
      "low": 17.619,
      "close": 18.116,
      "volume": 87230.1,
      "turnover": 1568365.7464
    },
    {
      "time": 1739923200000,
      "open": 18.116,
      "high": 18.819,
      "low": 17.831,
      "close": 18.79,
      "volume": 93446.5,
      "turnover": 1703039.5906
    },
    {
      "time": 1740009600000,
      "open": 18.79,
      "high": 19.721,
      "low": 18.283,
      "close": 18.936,
      "volume": 137850.4,
      "turnover": 2629692.2867
    },
    {
      "time": 1740096000000,
      "open": 18.936,
      "high": 19.4,
      "low": 17.975,
      "close": 18.222,
      "volume": 204224.3,
      "turnover": 3798695.098
    },
    {
      "time": 1740182400000,
      "open": 18.222,
      "high": 18.902,
      "low": 17.843,
      "close": 18.748,
      "volume": 41402.1,
      "turnover": 765347.1377
    },
    {
      "time": 1740268800000,
      "open": 18.748,
      "high": 19.663,
      "low": 18.277,
      "close": 18.649,
      "volume": 81396.2,
      "turnover": 1533888.7922
    },
    {
      "time": 1740355200000,
      "open": 18.649,
      "high": 19.152,
      "low": 18.202,
      "close": 18.773,
      "volume": 92660.5,
      "turnover": 1724353.0615
    },
    {
      "time": 1740441600000,
      "open": 18.773,
      "high": 21.368,
      "low": 18.693,
      "close": 19.959,
      "volume": 230703.3,
      "turnover": 4510222.7277
    },
    {
      "time": 1740528000000,
      "open": 19.959,
      "high": 20.743,
      "low": 19.361,
      "close": 19.602,
      "volume": 137081.9,
      "turnover": 2743301.1085
    },
    {
      "time": 1740614400000,
      "open": 19.602,
      "high": 20.037,
      "low": 17.236,
      "close": 17.545,
      "volume": 176391.2,
      "turnover": 3281358.8121
    },
    {
      "time": 1740700800000,
      "open": 17.545,
      "high": 18.521,
      "low": 17.302,
      "close": 18.511,
      "volume": 180623.4,
      "turnover": 3222474.5335
    },
    {
      "time": 1740787200000,
      "open": 18.511,
      "high": 18.904,
      "low": 17.743,
      "close": 18.207,
      "volume": 71254.6,
      "turnover": 1302415.1317
    },
    {
      "time": 1740873600000,
      "open": 18.207,
      "high": 19.121,
      "low": 17.927,
      "close": 18.519,
      "volume": 121325.2,
      "turnover": 2222113.9823
    },
    {
      "time": 1740960000000,
      "open": 18.519,
      "high": 18.756,
      "low": 17.807,
      "close": 17.838,
      "volume": 136598.8,
      "turnover": 2502817.676
    },
    {
      "time": 1741046400000,
      "open": 17.838,
      "high": 19.482,
      "low": 17.7,
      "close": 18.889,
      "volume": 200792.3,
      "turnover": 3694072.3795
    },
    {
      "time": 1741132800000,
      "open": 18.889,
      "high": 19.821,
      "low": 18.08,
      "close": 18.956,
      "volume": 104705.4,
      "turnover": 1987384.974
    },
    {
      "time": 1741219200000,
      "open": 18.956,
      "high": 19.183,
      "low": 17.963,
      "close": 18.368,
      "volume": 78956.2,
      "turnover": 1455596.4577
    },
    {
      "time": 1741305600000,
      "open": 18.368,
      "high": 18.637,
      "low": 17.976,
      "close": 18.435,
      "volume": 121643.0,
      "turnover": 2229025.4793
    },
    {
      "time": 1741392000000,
      "open": 18.435,
      "high": 19.0,
      "low": 18.265,
      "close": 18.684,
      "volume": 65477.6,
      "turnover": 1224141.6618
    },
    {
      "time": 1741478400000,
      "open": 18.684,
      "high": 18.877,
      "low": 17.717,
      "close": 17.79,
      "volume": 95040.8,
      "turnover": 1743254.3536
    },
    {
      "time": 1741564800000,
      "open": 17.79,
      "high": 18.084,
      "low": 17.251,
      "close": 17.42,
      "volume": 112256.1,
      "turnover": 1969921.3932
    },
    {
      "time": 1741651200000,
      "open": 17.42,
      "high": 17.753,
      "low": 17.26,
      "close": 17.581,
      "volume": 98444.7,
      "turnover": 1717230.5916
    },
    {
      "time": 1741737600000,
      "open": 17.581,
      "high": 17.712,
      "low": 17.3,
      "close": 17.353,
      "volume": 47832.5,
      "turnover": 832492.8601
    },
    {
      "time": 1741824000000,
      "open": 17.353,
      "high": 17.507,
      "low": 17.197,
      "close": 17.423,
      "volume": 46069.5,
      "turnover": 798829.399
    },
    {
      "time": 1741910400000,
      "open": 17.423,
      "high": 17.466,
      "low": 17.196,
      "close": 17.318,
      "volume": 35733.7,
      "turnover": 618821.7506
    },
    {
      "time": 1741996800000,
      "open": 17.318,
      "high": 17.471,
      "low": 17.247,
      "close": 17.403,
      "volume": 29165.6,
      "turnover": 506278.0589
    },
    {
      "time": 1742083200000,
      "open": 17.403,
      "high": 17.669,
      "low": 17.253,
      "close": 17.295,
      "volume": 36062.0,
      "turnover": 629254.0384
    },
    {
      "time": 1742169600000,
      "open": 17.295,
      "high": 17.434,
      "low": 17.06,
      "close": 17.115,
      "volume": 51880.5,
      "turnover": 891160.2026
    },
    {
      "time": 1742256000000,
      "open": 17.115,
      "high": 18.469,
      "low": 16.581,
      "close": 18.372,
      "volume": 205236.0,
      "turnover": 3563863.48
    },
    {
      "time": 1742342400000,
      "open": 18.372,
      "high": 19.198,
      "low": 18.14,
      "close": 19.065,
      "volume": 112380.4,
      "turnover": 2102848.7386
    },
    {
      "time": 1742428800000,
      "open": 19.065,
      "high": 19.513,
      "low": 18.635,
      "close": 19.217,
      "volume": 62367.9,
      "turnover": 1190354.1567
    },
    {
      "time": 1742515200000,
      "open": 19.217,
      "high": 19.322,
      "low": 18.559,
      "close": 18.65,
      "volume": 57391.1,
      "turnover": 1087706.3329
    },
    {
      "time": 1742601600000,
      "open": 18.65,
      "high": 19.009,
      "low": 17.41,
      "close": 17.728,
      "volume": 71290.8,
      "turnover": 1292388.1891
    },
    {
      "time": 1742688000000,
      "open": 17.728,
      "high": 17.753,
      "low": 16.607,
      "close": 17.374,
      "volume": 82032.0,
      "turnover": 1411852.949
    },
    {
      "time": 1742774400000,
      "open": 17.374,
      "high": 17.699,
      "low": 17.01,
      "close": 17.35,
      "volume": 54112.4,
      "turnover": 938236.4681
    },
    {
      "time": 1742860800000,
      "open": 17.35,
      "high": 17.695,
      "low": 17.204,
      "close": 17.514,
      "volume": 30435.2,
      "turnover": 531299.772
    },
    {
      "time": 1742947200000,
      "open": 17.514,
      "high": 17.654,
      "low": 17.245,
      "close": 17.462,
      "volume": 22068.7,
      "turnover": 384567.7719
    },
    {
      "time": 1743033600000,
      "open": 17.462,
      "high": 18.308,
      "low": 17.368,
      "close": 17.867,
      "volume": 113667.4,
      "turnover": 2034043.6408
    },
    {
      "time": 1743120000000,
      "open": 17.867,
      "high": 18.667,
      "low": 17.721,
      "close": 18.45,
      "volume": 98421.3,
      "turnover": 1795616.3129
    },
    {
      "time": 1743206400000,
      "open": 18.45,
      "high": 18.819,
      "low": 17.218,
      "close": 17.573,
      "volume": 109459.2,
      "turnover": 1956832.2314
    },
    {
      "time": 1743292800000,
      "open": 17.573,
      "high": 17.799,
      "low": 17.351,
      "close": 17.739,
      "volume": 30874.7,
      "turnover": 541951.7431
    },
    {
      "time": 1743379200000,
      "open": 17.739,
      "high": 18.257,
      "low": 17.326,
      "close": 17.926,
      "volume": 65547.9,
      "turnover": 1160477.5839
    },
    {
      "time": 1743465600000,
      "open": 17.926,
      "high": 18.419,
      "low": 11.313,
      "close": 13.58,
      "volume": 1567849.0,
      "turnover": 21552522.252
    },
    {
      "time": 1743552000000,
      "open": 13.58,
      "high": 15.539,
      "low": 12.681,
      "close": 14.627,
      "volume": 1087390.9,
      "turnover": 15559993.2055
    },
    {
      "time": 1743638400000,
      "open": 14.627,
      "high": 15.557,
      "low": 14.54,
      "close": 14.994,
      "volume": 288958.5,
      "turnover": 4333476.0378
    },
    {
      "time": 1743724800000,
      "open": 14.994,
      "high": 15.245,
      "low": 14.515,
      "close": 14.802,
      "volume": 231403.0,
      "turnover": 3438954.3741
    },
    {
      "time": 1743811200000,
      "open": 14.802,
      "high": 15.062,
      "low": 14.4,
      "close": 14.787,
      "volume": 104687.0,
      "turnover": 1531341.0523
    },
    {
      "time": 1743897600000,
      "open": 14.787,
      "high": 15.165,
      "low": 14.431,
      "close": 14.745,
      "volume": 201604.8,
      "turnover": 2990266.5858
    },
    {
      "time": 1743984000000,
      "open": 14.745,
      "high": 16.066,
      "low": 13.803,
      "close": 15.583,
      "volume": 341893.6,
      "turnover": 5098604.5364
    },
    {
      "time": 1744070400000,
      "open": 15.583,
      "high": 16.1,
      "low": 15.361,
      "close": 15.553,
      "volume": 150604.6,
      "turnover": 2365821.1597
    },
    {
      "time": 1744156800000,
      "open": 15.553,
      "high": 16.182,
      "low": 15.433,
      "close": 15.835,
      "volume": 186779.0,
      "turnover": 2945307.6205
    },
    {
      "time": 1744243200000,
      "open": 15.835,
      "high": 15.998,
      "low": 15.317,
      "close": 15.52,
      "volume": 167634.1,
      "turnover": 2627673.7517
    },
    {
      "time": 1744329600000,
      "open": 15.52,
      "high": 15.548,
      "low": 14.539,
      "close": 14.813,
      "volume": 182360.8,
      "turnover": 2709195.6547
    },
    {
      "time": 1744416000000,
      "open": 14.813,
      "high": 15.135,
      "low": 14.627,
      "close": 14.996,
      "volume": 89596.0,
      "turnover": 1338977.9992
    },
    {
      "time": 1744502400000,
      "open": 14.996,
      "high": 15.267,
      "low": 14.176,
      "close": 14.753,
      "volume": 290069.5,
      "turnover": 4237514.3277
    },
    {
      "time": 1744588800000,
      "open": 14.753,
      "high": 15.019,
      "low": 12.173,
      "close": 13.083,
      "volume": 555360.3,
      "turnover": 7412272.5542
    },
    {
      "time": 1744675200000,
      "open": 13.083,
      "high": 15.303,
      "low": 11.474,
      "close": 13.307,
      "volume": 843123.6,
      "turnover": 11607377.9869
    },
    {
      "time": 1744761600000,
      "open": 13.307,
      "high": 14.523,
      "low": 13.111,
      "close": 13.642,
      "volume": 410289.4,
      "turnover": 5706329.8247
    },
    {
      "time": 1744848000000,
      "open": 13.642,
      "high": 14.173,
      "low": 13.607,
      "close": 14.033,
      "volume": 141406.8,
      "turnover": 1963636.6299
    },
    {
      "time": 1744934400000,
      "open": 14.033,
      "high": 14.531,
      "low": 13.51,
      "close": 13.915,
      "volume": 470540.8,
      "turnover": 6565217.6492
    },
    {
      "time": 1745020800000,
      "open": 13.915,
      "high": 14.917,
      "low": 13.835,
      "close": 14.856,
      "volume": 180858.0,
      "turnover": 2577560.0916
    },
    {
      "time": 1745107200000,
      "open": 14.856,
      "high": 15.493,
      "low": 14.792,
      "close": 15.017,
      "volume": 95088.2,
      "turnover": 1436840.7717
    },
    {
      "time": 1745193600000,
      "open": 15.017,
      "high": 15.568,
      "low": 13.737,
      "close": 14.479,
      "volume": 171534.5,
      "turnover": 2490953.1311
    },
    {
      "time": 1745280000000,
      "open": 14.479,
      "high": 15.615,
      "low": 14.384,
      "close": 15.453,
      "volume": 83914.6,
      "turnover": 1258780.405
    },
    {
      "time": 1745366400000,
      "open": 15.453,
      "high": 16.16,
      "low": 13.168,
      "close": 14.167,
      "volume": 333303.8,
      "turnover": 4804193.2694
    },
    {
      "time": 1745452800000,
      "open": 14.167,
      "high": 14.509,
      "low": 12.9,
      "close": 13.328,
      "volume": 733178.8,
      "turnover": 10115271.3399
    },
    {
      "time": 1745539200000,
      "open": 13.328,
      "high": 13.762,
      "low": 12.973,
      "close": 13.11,
      "volume": 160736.4,
      "turnover": 2148762.986
    },
    {
      "time": 1745625600000,
      "open": 13.11,
      "high": 13.434,
      "low": 12.992,
      "close": 13.191,
      "volume": 61849.9,
      "turnover": 818884.2298
    },
    {
      "time": 1745712000000,
      "open": 13.191,
      "high": 13.357,
      "low": 12.782,
      "close": 13.106,
      "volume": 70123.1,
      "turnover": 918957.0413
    },
    {
      "time": 1745798400000,
      "open": 13.106,
      "high": 13.759,
      "low": 12.762,
      "close": 13.219,
      "volume": 145579.6,
      "turnover": 1926859.7984
    },
    {
      "time": 1745884800000,
      "open": 13.219,
      "high": 13.758,
      "low": 12.939,
      "close": 13.076,
      "volume": 117913.5,
      "turnover": 1563998.9746
    },
    {
      "time": 1745971200000,
      "open": 13.076,
      "high": 13.415,
      "low": 12.972,
      "close": 13.311,
      "volume": 42043.4,
      "turnover": 553672.6546
    },
    {
      "time": 1746057600000,
      "open": 13.311,
      "high": 13.45,
      "low": 13.157,
      "close": 13.193,
      "volume": 34146.6,
      "turnover": 453736.2286
    },
    {
      "time": 1746144000000,
      "open": 13.193,
      "high": 13.365,
      "low": 13.111,
      "close": 13.278,
      "volume": 30096.4,
      "turnover": 398767.8146
    },
    {
      "time": 1746230400000,
      "open": 13.278,
      "high": 14.654,
      "low": 12.817,
      "close": 14.207,
      "volume": 241192.2,
      "turnover": 3364244.094
    },
    {
      "time": 1746316800000,
      "open": 14.207,
      "high": 14.873,
      "low": 14.058,
      "close": 14.505,
      "volume": 418164.2,
      "turnover": 6053246.0351
    },
    {
      "time": 1746403200000,
      "open": 14.505,
      "high": 15.177,
      "low": 14.26,
      "close": 15.028,
      "volume": 120075.8,
      "turnover": 1758279.2682
    },
    {
      "time": 1746489600000,
      "open": 15.028,
      "high": 15.483,
      "low": 14.626,
      "close": 15.257,
      "volume": 96554.2,
      "turnover": 1451804.6029
    },
    {
      "time": 1746576000000,
      "open": 15.257,
      "high": 15.513,
      "low": 14.366,
      "close": 14.571,
      "volume": 68840.1,
      "turnover": 1028201.2453
    },
    {
      "time": 1746662400000,
      "open": 14.571,
      "high": 15.045,
      "low": 14.379,
      "close": 14.854,
      "volume": 64776.4,
      "turnover": 954114.6901
    },
    {
      "time": 1746748800000,
      "open": 14.854,
      "high": 15.203,
      "low": 14.368,
      "close": 14.528,
      "volume": 75855.5,
      "turnover": 1122105.1517
    },
    {
      "time": 1746835200000,
      "open": 14.528,
      "high": 14.539,
      "low": 13.322,
      "close": 13.866,
      "volume": 116940.8,
      "turnover": 1614306.2961
    },
    {
      "time": 1746921600000,
      "open": 13.866,
      "high": 14.257,
      "low": 13.584,
      "close": 14.03,
      "volume": 102145.5,
      "turnover": 1435874.9636
    },
    {
      "time": 1747008000000,
      "open": 14.03,
      "high": 14.485,
      "low": 12.743,
      "close": 13.267,
      "volume": 453733.7,
      "turnover": 6078563.0677
    },
    {
      "time": 1747094400000,
      "open": 13.267,
      "high": 13.324,
      "low": 11.64,
      "close": 12.813,
      "volume": 414490.1,
      "turnover": 5184611.6828
    },
    {
      "time": 1747180800000,
      "open": 12.813,
      "high": 13.083,
      "low": 12.222,
      "close": 12.561,
      "volume": 204709.0,
      "turnover": 2586415.1101
    },
    {
      "time": 1747267200000,
      "open": 12.561,
      "high": 13.217,
      "low": 12.0,
      "close": 13.086,
      "volume": 312025.4,
      "turnover": 3980651.4283
    },
    {
      "time": 1747353600000,
      "open": 13.086,
      "high": 13.103,
      "low": 12.666,
      "close": 12.851,
      "volume": 59180.3,
      "turnover": 761409.2207
    },
    {
      "time": 1747440000000,
      "open": 12.851,
      "high": 13.343,
      "low": 12.559,
      "close": 12.697,
      "volume": 112360.7,
      "turnover": 1465471.0993
    },
    {
      "time": 1747526400000,
      "open": 12.697,
      "high": 13.178,
      "low": 12.664,
      "close": 13.064,
      "volume": 76095.3,
      "turnover": 984598.0898
    },
    {
      "time": 1747612800000,
      "open": 13.064,
      "high": 13.068,
      "low": 12.581,
      "close": 12.749,
      "volume": 87466.3,
      "turnover": 1118503.189
    },
    {
      "time": 1747699200000,
      "open": 12.749,
      "high": 12.937,
      "low": 12.56,
      "close": 12.88,
      "volume": 66078.1,
      "turnover": 842462.8835
    },
    {
      "time": 1747785600000,
      "open": 12.88,
      "high": 12.993,
      "low": 12.649,
      "close": 12.738,
      "volume": 48601.5,
      "turnover": 622212.9412
    },
    {
      "time": 1747872000000,
      "open": 12.738,
      "high": 12.834,
      "low": 12.295,
      "close": 12.513,
      "volume": 133816.6,
      "turnover": 1684486.612
    },
    {
      "time": 1747958400000,
      "open": 12.513,
      "high": 12.778,
      "low": 12.324,
      "close": 12.492,
      "volume": 93031.4,
      "turnover": 1165883.0812
    },
    {
      "time": 1748044800000,
      "open": 12.492,
      "high": 12.683,
      "low": 12.205,
      "close": 12.492,
      "volume": 63837.3,
      "turnover": 795039.6712
    },
    {
      "time": 1748131200000,
      "open": 12.492,
      "high": 12.757,
      "low": 12.062,
      "close": 12.665,
      "volume": 117747.4,
      "turnover": 1464279.0096
    },
    {
      "time": 1748217600000,
      "open": 12.665,
      "high": 13.047,
      "low": 12.476,
      "close": 12.536,
      "volume": 59406.7,
      "turnover": 758990.7622
    },
    {
      "time": 1748304000000,
      "open": 12.536,
      "high": 12.564,
      "low": 12.323,
      "close": 12.36,
      "volume": 41082.6,
      "turnover": 511388.8492
    },
    {
      "time": 1748390400000,
      "open": 12.36,
      "high": 12.57,
      "low": 12.321,
      "close": 12.502,
      "volume": 29862.6,
      "turnover": 371570.3331
    },
    {
      "time": 1748476800000,
      "open": 12.502,
      "high": 14.34,
      "low": 12.432,
      "close": 14.139,
      "volume": 583636.6,
      "turnover": 8011955.3324
    },
    {
      "time": 1748563200000,
      "open": 14.139,
      "high": 14.766,
      "low": 13.711,
      "close": 14.027,
      "volume": 531282.7,
      "turnover": 7540197.4118
    },
    {
      "time": 1748649600000,
      "open": 14.027,
      "high": 14.432,
      "low": 13.783,
      "close": 14.162,
      "volume": 222350.0,
      "turnover": 3122042.373
    },
    {
      "time": 1748736000000,
      "open": 14.162,
      "high": 14.569,
      "low": 13.905,
      "close": 14.262,
      "volume": 100397.3,
      "turnover": 1427566.2981
    },
    {
      "time": 1748822400000,
      "open": 14.262,
      "high": 15.447,
      "low": 8.368,
      "close": 9.7,
      "volume": 6398683.2,
      "turnover": 71813524.7591
    },
    {
      "time": 1748908800000,
      "open": 9.7,
      "high": 9.748,
      "low": 8.404,
      "close": 8.965,
      "volume": 3536582.2,
      "turnover": 32348619.667
    },
    {
      "time": 1748995200000,
      "open": 8.965,
      "high": 10.714,
      "low": 8.946,
      "close": 9.872,
      "volume": 2139984.7,
      "turnover": 21042573.5335
    },
    {
      "time": 1749081600000,
      "open": 9.872,
      "high": 10.302,
      "low": 9.569,
      "close": 9.894,
      "volume": 766162.6,
      "turnover": 7598678.9205
    },
    {
      "time": 1749168000000,
      "open": 9.894,
      "high": 10.578,
      "low": 9.593,
      "close": 10.529,
      "volume": 657168.3,
      "turnover": 6573065.6385
    },
    {
      "time": 1749254400000,
      "open": 10.529,
      "high": 10.7,
      "low": 10.166,
      "close": 10.513,
      "volume": 209142.1,
      "turnover": 2182770.3097
    },
    {
      "time": 1749340800000,
      "open": 10.513,
      "high": 10.971,
      "low": 9.698,
      "close": 10.016,
      "volume": 629611.6,
      "turnover": 6424681.4905
    },
    {
      "time": 1749427200000,
      "open": 10.016,
      "high": 10.186,
      "low": 8.184,
      "close": 9.203,
      "volume": 1764250.0,
      "turnover": 15787951.5589
    },
    {
      "time": 1749513600000,
      "open": 9.203,
      "high": 10.567,
      "low": 8.951,
      "close": 9.395,
      "volume": 1208053.2,
      "turnover": 11676094.0659
    },
    {
      "time": 1749600000000,
      "open": 9.395,
      "high": 9.548,
      "low": 9.161,
      "close": 9.242,
      "volume": 197451.2,
      "turnover": 1840592.2958
    },
    {
      "time": 1749686400000,
      "open": 9.242,
      "high": 9.324,
      "low": 8.767,
      "close": 8.873,
      "volume": 244755.1,
      "turnover": 2222636.8325
    },
    {
      "time": 1749772800000,
      "open": 8.873,
      "high": 9.015,
      "low": 8.516,
      "close": 8.975,
      "volume": 187860.3,
      "turnover": 1653233.8052
    },
    {
      "time": 1749859200000,
      "open": 8.975,
      "high": 9.059,
      "low": 8.754,
      "close": 8.85,
      "volume": 131418.5,
      "turnover": 1168942.657
    },
    {
      "time": 1749945600000,
      "open": 8.85,
      "high": 9.004,
      "low": 8.569,
      "close": 8.823,
      "volume": 125349.2,
      "turnover": 1099716.6481
    },
    {
      "time": 1750032000000,
      "open": 8.823,
      "high": 8.98,
      "low": 8.742,
      "close": 8.808,
      "volume": 64118.2,
      "turnover": 568689.2823
    },
    {
      "time": 1750118400000,
      "open": 8.808,
      "high": 8.943,
      "low": 8.653,
      "close": 8.792,
      "volume": 54741.8,
      "turnover": 482529.9206
    },
    {
      "time": 1750204800000,
      "open": 8.792,
      "high": 8.852,
      "low": 8.416,
      "close": 8.69,
      "volume": 72245.2,
      "turnover": 624430.1501
    },
    {
      "time": 1750291200000,
      "open": 8.69,
      "high": 8.729,
      "low": 8.439,
      "close": 8.614,
      "volume": 43786.7,
      "turnover": 375592.9495
    },
    {
      "time": 1750377600000,
      "open": 8.614,
      "high": 8.626,
      "low": 7.572,
      "close": 7.852,
      "volume": 189560.3,
      "turnover": 1546063.0121
    },
    {
      "time": 1750464000000,
      "open": 7.852,
      "high": 8.089,
      "low": 7.547,
      "close": 7.821,
      "volume": 213953.9,
      "turnover": 1664764.4073
    },
    {
      "time": 1750550400000,
      "open": 7.821,
      "high": 7.904,
      "low": 7.607,
      "close": 7.873,
      "volume": 141263.8,
      "turnover": 1093054.6741
    },
    {
      "time": 1750636800000,
      "open": 7.873,
      "high": 8.231,
      "low": 7.665,
      "close": 8.052,
      "volume": 106876.9,
      "turnover": 845608.8743
    },
    {
      "time": 1750723200000,
      "open": 8.052,
      "high": 9.452,
      "low": 4.986,
      "close": 8.834,
      "volume": 4377495.5,
      "turnover": 30583624.3596
    },
    {
      "time": 1750809600000,
      "open": 8.834,
      "high": 9.17,
      "low": 7.644,
      "close": 8.18,
      "volume": 2286413.8,
      "turnover": 19008000.627
    },
    {
      "time": 1750896000000,
      "open": 8.18,
      "high": 9.096,
      "low": 8.115,
      "close": 8.969,
      "volume": 595016.5,
      "turnover": 5174160.6936
    },
    {
      "time": 1750982400000,
      "open": 8.969,
      "high": 9.112,
      "low": 8.678,
      "close": 8.83,
      "volume": 278012.9,
      "turnover": 2459085.2474
    },
    {
      "time": 1751068800000,
      "open": 8.83,
      "high": 8.963,
      "low": 8.639,
      "close": 8.875,
      "volume": 192619.7,
      "turnover": 1692180.7243
    },
    {
      "time": 1751155200000,
      "open": 8.875,
      "high": 9.013,
      "low": 8.033,
      "close": 8.141,
      "volume": 736721.9,
      "turnover": 6109301.1383
    },
    {
      "time": 1751241600000,
      "open": 8.141,
      "high": 8.282,
      "low": 7.251,
      "close": 7.532,
      "volume": 662506.4,
      "turnover": 5074677.5399
    },
    {
      "time": 1751328000000,
      "open": 7.532,
      "high": 7.623,
      "low": 7.072,
      "close": 7.461,
      "volume": 294781.1,
      "turnover": 2170630.7261
    },
    {
      "time": 1751414400000,
      "open": 7.461,
      "high": 7.498,
      "low": 7.343,
      "close": 7.464,
      "volume": 126496.1,
      "turnover": 937778.2816
    },
    {
      "time": 1751500800000,
      "open": 7.464,
      "high": 7.696,
      "low": 7.297,
      "close": 7.512,
      "volume": 215838.9,
      "turnover": 1612222.5758
    },
    {
      "time": 1751587200000,
      "open": 7.512,
      "high": 7.536,
      "low": 7.384,
      "close": 7.417,
      "volume": 93423.7,
      "turnover": 696456.004
    },
    {
      "time": 1751673600000,
      "open": 7.417,
      "high": 7.7,
      "low": 7.358,
      "close": 7.573,
      "volume": 188907.0,
      "turnover": 1415271.4833
    },
    {
      "time": 1751760000000,
      "open": 7.573,
      "high": 7.677,
      "low": 7.502,
      "close": 7.591,
      "volume": 86521.1,
      "turnover": 657393.1449
    },
    {
      "time": 1751846400000,
      "open": 7.591,
      "high": 7.763,
      "low": 7.531,
      "close": 7.674,
      "volume": 92052.0,
      "turnover": 703847.5546
    },
    {
      "time": 1751932800000,
      "open": 7.674,
      "high": 7.836,
      "low": 7.638,
      "close": 7.82,
      "volume": 114867.1,
      "turnover": 890819.8344
    },
    {
      "time": 1752019200000,
      "open": 7.82,
      "high": 7.908,
      "low": 7.627,
      "close": 7.815,
      "volume": 90065.0,
      "turnover": 701998.9963
    },
    {
      "time": 1752105600000,
      "open": 7.815,
      "high": 7.892,
      "low": 7.629,
      "close": 7.846,
      "volume": 88518.5,
      "turnover": 687201.1072
    },
    {
      "time": 1752192000000,
      "open": 7.846,
      "high": 8.259,
      "low": 7.536,
      "close": 7.586,
      "volume": 402339.9,
      "turnover": 3170522.7078
    },
    {
      "time": 1752278400000,
      "open": 7.586,
      "high": 7.658,
      "low": 7.469,
      "close": 7.609,
      "volume": 88589.3,
      "turnover": 670040.8874
    },
    {
      "time": 1752364800000,
      "open": 7.609,
      "high": 7.648,
      "low": 7.504,
      "close": 7.537,
      "volume": 51914.7,
      "turnover": 393827.0514
    },
    {
      "time": 1752451200000,
      "open": 7.537,
      "high": 7.624,
      "low": 7.5,
      "close": 7.522,
      "volume": 71868.2,
      "turnover": 543816.7383
    },
    {
      "time": 1752537600000,
      "open": 7.522,
      "high": 7.705,
      "low": 7.266,
      "close": 7.36,
      "volume": 239178.2,
      "turnover": 1786017.9797
    },
    {
      "time": 1752624000000,
      "open": 7.36,
      "high": 8.141,
      "low": 7.277,
      "close": 7.986,
      "volume": 186696.9,
      "turnover": 1452090.0429
    },
    {
      "time": 1752710400000,
      "open": 7.986,
      "high": 8.578,
      "low": 7.795,
      "close": 7.93,
      "volume": 229269.4,
      "turnover": 1864213.7164
    },
    {
      "time": 1752796800000,
      "open": 7.93,
      "high": 8.134,
      "low": 7.847,
      "close": 7.982,
      "volume": 114466.3,
      "turnover": 916056.1121
    },
    {
      "time": 1752883200000,
      "open": 7.982,
      "high": 8.075,
      "low": 7.132,
      "close": 7.243,
      "volume": 328651.5,
      "turnover": 2456847.5121
    },
    {
      "time": 1752969600000,
      "open": 7.243,
      "high": 7.491,
      "low": 7.185,
      "close": 7.422,
      "volume": 208837.1,
      "turnover": 1539401.4951
    },
    {
      "time": 1753056000000,
      "open": 7.422,
      "high": 7.57,
      "low": 7.331,
      "close": 7.469,
      "volume": 101412.5,
      "turnover": 755900.2797
    },
    {
      "time": 1753142400000,
      "open": 7.469,
      "high": 7.515,
      "low": 7.297,
      "close": 7.416,
      "volume": 100331.7,
      "turnover": 743295.2898
    },
    {
      "time": 1753228800000,
      "open": 7.416,
      "high": 7.461,
      "low": 7.145,
      "close": 7.23,
      "volume": 99368.1,
      "turnover": 726508.6973
    },
    {
      "time": 1753315200000,
      "open": 7.23,
      "high": 7.355,
      "low": 7.055,
      "close": 7.253,
      "volume": 107931.5,
      "turnover": 778057.8943
    },
    {
      "time": 1753401600000,
      "open": 7.253,
      "high": 7.446,
      "low": 7.196,
      "close": 7.367,
      "volume": 101126.9,
      "turnover": 740587.467
    },
    {
      "time": 1753488000000,
      "open": 7.367,
      "high": 7.564,
      "low": 7.352,
      "close": 7.499,
      "volume": 65219.5,
      "turnover": 487457.118
    },
    {
      "time": 1753574400000,
      "open": 7.499,
      "high": 7.538,
      "low": 7.264,
      "close": 7.507,
      "volume": 82531.9,
      "turnover": 614116.3782
    },
    {
      "time": 1753660800000,
      "open": 7.507,
      "high": 7.542,
      "low": 7.293,
      "close": 7.354,
      "volume": 100928.0,
      "turnover": 749282.6768
    },
    {
      "time": 1753747200000,
      "open": 7.354,
      "high": 7.475,
      "low": 7.265,
      "close": 7.334,
      "volume": 73787.2,
      "turnover": 542331.8199
    },
    {
      "time": 1753833600000,
      "open": 7.334,
      "high": 7.536,
      "low": 7.243,
      "close": 7.5,
      "volume": 108392.2,
      "turnover": 798437.2489
    },
    {
      "time": 1753920000000,
      "open": 7.5,
      "high": 7.677,
      "low": 7.301,
      "close": 7.319,
      "volume": 95111.5,
      "turnover": 713896.518
    },
    {
      "time": 1754006400000,
      "open": 7.319,
      "high": 7.327,
      "low": 6.962,
      "close": 7.022,
      "volume": 73797.9,
      "turnover": 527181.2979
    },
    {
      "time": 1754092800000,
      "open": 7.022,
      "high": 7.144,
      "low": 6.887,
      "close": 6.926,
      "volume": 42808.3,
      "turnover": 300133.8055
    },
    {
      "time": 1754179200000,
      "open": 6.926,
      "high": 7.273,
      "low": 6.791,
      "close": 7.248,
      "volume": 32205.0,
      "turnover": 225262.2496
    },
    {
      "time": 1754265600000,
      "open": 7.248,
      "high": 7.761,
      "low": 7.242,
      "close": 7.757,
      "volume": 119249.0,
      "turnover": 894197.593
    },
    {
      "time": 1754352000000,
      "open": 7.757,
      "high": 8.351,
      "low": 7.518,
      "close": 7.64,
      "volume": 224294.3,
      "turnover": 1779365.0944
    },
    {
      "time": 1754438400000,
      "open": 7.64,
      "high": 8.411,
      "low": 7.557,
      "close": 8.407,
      "volume": 96646.6,
      "turnover": 766313.8392
    },
    {
      "time": 1754524800000,
      "open": 8.407,
      "high": 8.71,
      "low": 8.234,
      "close": 8.512,
      "volume": 122458.1,
      "turnover": 1036689.3579
    },
    {
      "time": 1754611200000,
      "open": 8.512,
      "high": 8.855,
      "low": 8.368,
      "close": 8.395,
      "volume": 56597.5,
      "turnover": 482210.2956
    },
    {
      "time": 1754697600000,
      "open": 8.395,
      "high": 8.616,
      "low": 8.164,
      "close": 8.206,
      "volume": 125145.1,
      "turnover": 1048098.3874
    },
    {
      "time": 1754784000000,
      "open": 8.206,
      "high": 8.251,
      "low": 7.806,
      "close": 7.88,
      "volume": 57306.8,
      "turnover": 458995.5811
    },
    {
      "time": 1754870400000,
      "open": 7.88,
      "high": 8.039,
      "low": 7.449,
      "close": 7.488,
      "volume": 65017.6,
      "turnover": 507961.0171
    },
    {
      "time": 1754956800000,
      "open": 7.488,
      "high": 7.688,
      "low": 7.402,
      "close": 7.48,
      "volume": 65747.8,
      "turnover": 496413.969
    },
    {
      "time": 1755043200000,
      "open": 7.48,
      "high": 7.705,
      "low": 7.379,
      "close": 7.507,
      "volume": 114888.3,
      "turnover": 864986.5739
    },
    {
      "time": 1755129600000,
      "open": 7.507,
      "high": 7.571,
      "low": 7.062,
      "close": 7.158,
      "volume": 78143.5,
      "turnover": 568799.7947
    },
    {
      "time": 1755216000000,
      "open": 7.158,
      "high": 7.373,
      "low": 7.132,
      "close": 7.341,
      "volume": 55168.6,
      "turnover": 399607.9728
    },
    {
      "time": 1755302400000,
      "open": 7.341,
      "high": 7.452,
      "low": 7.27,
      "close": 7.4,
      "volume": 29530.3,
      "turnover": 217112.8947
    },
    {
      "time": 1755388800000,
      "open": 7.4,
      "high": 7.483,
      "low": 7.361,
      "close": 7.426,
      "volume": 38590.5,
      "turnover": 286169.6628
    },
    {
      "time": 1755475200000,
      "open": 7.426,
      "high": 7.503,
      "low": 7.195,
      "close": 7.32,
      "volume": 51694.5,
      "turnover": 380138.8086
    },
    {
      "time": 1755561600000,
      "open": 7.32,
      "high": 7.362,
      "low": 7.077,
      "close": 7.081,
      "volume": 19382.4,
      "turnover": 140501.9665
    },
    {
      "time": 1755648000000,
      "open": 7.081,
      "high": 7.298,
      "low": 6.96,
      "close": 7.237,
      "volume": 33694.8,
      "turnover": 240633.0204
    },
    {
      "time": 1755734400000,
      "open": 7.237,
      "high": 7.335,
      "low": 7.076,
      "close": 7.101,
      "volume": 15735.0,
      "turnover": 113406.2054
    },
    {
      "time": 1755820800000,
      "open": 7.101,
      "high": 7.246,
      "low": 6.954,
      "close": 7.178,
      "volume": 86261.2,
      "turnover": 615895.6937
    },
    {
      "time": 1755907200000,
      "open": 7.178,
      "high": 7.25,
      "low": 6.885,
      "close": 7.148,
      "volume": 104245.7,
      "turnover": 738140.3898
    },
    {
      "time": 1755993600000,
      "open": 7.148,
      "high": 7.198,
      "low": 6.891,
      "close": 6.93,
      "volume": 43845.3,
      "turnover": 308245.1131
    },
    {
      "time": 1756080000000,
      "open": 6.93,
      "high": 7.128,
      "low": 6.909,
      "close": 7.026,
      "volume": 89747.5,
      "turnover": 631098.8157
    },
    {
      "time": 1756166400000,
      "open": 7.026,
      "high": 7.393,
      "low": 7.0,
      "close": 7.358,
      "volume": 156314.3,
      "turnover": 1130486.0535
    },
    {
      "time": 1756252800000,
      "open": 7.358,
      "high": 7.581,
      "low": 7.297,
      "close": 7.578,
      "volume": 46683.1,
      "turnover": 347978.0304
    },
    {
      "time": 1756339200000,
      "open": 7.578,
      "high": 7.638,
      "low": 7.364,
      "close": 7.491,
      "volume": 38770.1,
      "turnover": 289902.2062
    },
    {
      "time": 1756425600000,
      "open": 7.491,
      "high": 7.629,
      "low": 7.321,
      "close": 7.562,
      "volume": 55524.6,
      "turnover": 417515.8288
    },
    {
      "time": 1756512000000,
      "open": 7.562,
      "high": 7.757,
      "low": 7.494,
      "close": 7.7,
      "volume": 30112.0,
      "turnover": 228396.4366
    },
    {
      "time": 1756598400000,
      "open": 7.7,
      "high": 7.779,
      "low": 7.393,
      "close": 7.411,
      "volume": 33312.5,
      "turnover": 253300.2071
    },
    {
      "time": 1756684800000,
      "open": 7.411,
      "high": 7.529,
      "low": 7.217,
      "close": 7.521,
      "volume": 46705.2,
      "turnover": 343699.3075
    },
    {
      "time": 1756771200000,
      "open": 7.521,
      "high": 7.563,
      "low": 7.262,
      "close": 7.349,
      "volume": 31273.0,
      "turnover": 231483.3341
    },
    {
      "time": 1756857600000,
      "open": 7.349,
      "high": 7.457,
      "low": 7.25,
      "close": 7.417,
      "volume": 27412.7,
      "turnover": 200957.4574
    },
    {
      "time": 1756944000000,
      "open": 7.417,
      "high": 7.5,
      "low": 7.201,
      "close": 7.261,
      "volume": 39714.2,
      "turnover": 291842.4873
    },
    {
      "time": 1757030400000,
      "open": 7.261,
      "high": 7.345,
      "low": 7.158,
      "close": 7.253,
      "volume": 37582.4,
      "turnover": 272323.745
    },
    {
      "time": 1757116800000,
      "open": 7.253,
      "high": 7.282,
      "low": 7.068,
      "close": 7.114,
      "volume": 24555.7,
      "turnover": 175585.39
    },
    {
      "time": 1757203200000,
      "open": 7.114,
      "high": 7.134,
      "low": 6.966,
      "close": 7.005,
      "volume": 63654.4,
      "turnover": 448814.4597
    },
    {
      "time": 1757289600000,
      "open": 7.005,
      "high": 7.067,
      "low": 6.892,
      "close": 7.024,
      "volume": 55294.4,
      "turnover": 386649.2075
    },
    {
      "time": 1757376000000,
      "open": 7.024,
      "high": 7.332,
      "low": 6.832,
      "close": 6.928,
      "volume": 81393.7,
      "turnover": 577928.1493
    },
    {
      "time": 1757462400000,
      "open": 6.928,
      "high": 7.034,
      "low": 6.912,
      "close": 6.992,
      "volume": 33027.2,
      "turnover": 230516.5184
    },
    {
      "time": 1757548800000,
      "open": 6.992,
      "high": 7.045,
      "low": 6.911,
      "close": 6.973,
      "volume": 27019.7,
      "turnover": 188408.0169
    },
    {
      "time": 1757635200000,
      "open": 6.973,
      "high": 7.06,
      "low": 6.89,
      "close": 7.0,
      "volume": 50421.1,
      "turnover": 350365.257
    },
    {
      "time": 1757721600000,
      "open": 7.0,
      "high": 7.091,
      "low": 6.925,
      "close": 6.998,
      "volume": 40191.9,
      "turnover": 281577.0354
    },
    {
      "time": 1757808000000,
      "open": 6.998,
      "high": 7.018,
      "low": 6.906,
      "close": 6.929,
      "volume": 23470.2,
      "turnover": 163498.0002
    },
    {
      "time": 1757894400000,
      "open": 6.929,
      "high": 7.019,
      "low": 6.836,
      "close": 7.008,
      "volume": 53141.0,
      "turnover": 366835.5551
    },
    {
      "time": 1757980800000,
      "open": 7.008,
      "high": 7.06,
      "low": 6.931,
      "close": 7.05,
      "volume": 34594.1,
      "turnover": 242219.5764
    },
    {
      "time": 1758067200000,
      "open": 7.05,
      "high": 7.366,
      "low": 6.757,
      "close": 7.167,
      "volume": 207086.4,
      "turnover": 1471379.0748
    },
    {
      "time": 1758153600000,
      "open": 7.167,
      "high": 9.196,
      "low": 7.064,
      "close": 8.052,
      "volume": 1648189.6,
      "turnover": 13343309.1902
    },
    {
      "time": 1758240000000,
      "open": 8.052,
      "high": 10.078,
      "low": 7.963,
      "close": 8.638,
      "volume": 1861757.1,
      "turnover": 16646628.5222
    },
    {
      "time": 1758326400000,
      "open": 8.638,
      "high": 10.398,
      "low": 8.535,
      "close": 10.092,
      "volume": 736500.2,
      "turnover": 6862998.2357
    },
    {
      "time": 1758412800000,
      "open": 10.092,
      "high": 12.975,
      "low": 9.915,
      "close": 11.402,
      "volume": 2766531.9,
      "turnover": 32358980.3538
    },
    {
      "time": 1758499200000,
      "open": 11.402,
      "high": 11.536,
      "low": 10.409,
      "close": 10.476,
      "volume": 507726.4,
      "turnover": 5605032.9598
    },
    {
      "time": 1758585600000,
      "open": 10.476,
      "high": 10.882,
      "low": 9.832,
      "close": 9.856,
      "volume": 219402.3,
      "turnover": 2284556.7469
    },
    {
      "time": 1758672000000,
      "open": 9.856,
      "high": 10.381,
      "low": 9.723,
      "close": 9.816,
      "volume": 271535.0,
      "turnover": 2712099.0482
    },
    {
      "time": 1758758400000,
      "open": 9.816,
      "high": 9.823,
      "low": 9.105,
      "close": 9.164,
      "volume": 140201.3,
      "turnover": 1325628.5791
    },
    {
      "time": 1758844800000,
      "open": 9.164,
      "high": 9.622,
      "low": 9.164,
      "close": 9.477,
      "volume": 71016.6,
      "turnover": 665877.2711
    },
    {
      "time": 1758931200000,
      "open": 9.477,
      "high": 9.932,
      "low": 9.242,
      "close": 9.302,
      "volume": 107364.6,
      "turnover": 1028192.2656
    },
    {
      "time": 1759017600000,
      "open": 9.302,
      "high": 9.444,
      "low": 9.086,
      "close": 9.354,
      "volume": 59073.3,
      "turnover": 547899.8307
    },
    {
      "time": 1759104000000,
      "open": 9.354,
      "high": 10.846,
      "low": 8.981,
      "close": 9.523,
      "volume": 513101.6,
      "turnover": 4938214.7712
    },
    {
      "time": 1759190400000,
      "open": 9.523,
      "high": 9.688,
      "low": 9.208,
      "close": 9.484,
      "volume": 147462.0,
      "turnover": 1394578.2332
    },
    {
      "time": 1759276800000,
      "open": 9.484,
      "high": 11.314,
      "low": 9.069,
      "close": 11.236,
      "volume": 725779.1,
      "turnover": 7474025.9028
    },
    {
      "time": 1759363200000,
      "open": 11.236,
      "high": 13.45,
      "low": 11.13,
      "close": 12.366,
      "volume": 765807.8,
      "turnover": 9412613.6804
    },
    {
      "time": 1759449600000,
      "open": 12.366,
      "high": 13.131,
      "low": 12.277,
      "close": 12.381,
      "volume": 186513.0,
      "turnover": 2348674.0676
    },
    {
      "time": 1759536000000,
      "open": 12.381,
      "high": 12.702,
      "low": 12.093,
      "close": 12.219,
      "volume": 101958.7,
      "turnover": 1256959.022
    },
    {
      "time": 1759622400000,
      "open": 12.219,
      "high": 12.922,
      "low": 11.585,
      "close": 11.669,
      "volume": 96964.0,
      "turnover": 1171890.2641
    },
    {
      "time": 1759708800000,
      "open": 11.669,
      "high": 12.407,
      "low": 11.62,
      "close": 12.008,
      "volume": 82089.6,
      "turnover": 976698.1508
    },
    {
      "time": 1759795200000,
      "open": 12.008,
      "high": 13.603,
      "low": 11.666,
      "close": 12.928,
      "volume": 452423.2,
      "turnover": 5897912.1944
    },
    {
      "time": 1759881600000,
      "open": 12.928,
      "high": 13.13,
      "low": 11.317,
      "close": 11.358,
      "volume": 250528.1,
      "turnover": 3087943.8558
    },
    {
      "time": 1759968000000,
      "open": 11.358,
      "high": 11.531,
      "low": 10.569,
      "close": 11.137,
      "volume": 192987.9,
      "turnover": 2135095.7058
    },
    {
      "time": 1760054400000,
      "open": 11.137,
      "high": 11.296,
      "low": 1.52,
      "close": 5.534,
      "volume": 938012.2,
      "turnover": 5661351.4103
    },
    {
      "time": 1760140800000,
      "open": 5.534,
      "high": 6.768,
      "low": 5.361,
      "close": 5.635,
      "volume": 954835.6,
      "turnover": 5742841.6931
    },
    {
      "time": 1760227200000,
      "open": 5.635,
      "high": 6.083,
      "low": 5.307,
      "close": 5.864,
      "volume": 427956.3,
      "turnover": 2414951.5474
    },
    {
      "time": 1760313600000,
      "open": 5.864,
      "high": 6.431,
      "low": 5.718,
      "close": 6.358,
      "volume": 288434.2,
      "turnover": 1736268.8402
    },
    {
      "time": 1760400000000,
      "open": 6.358,
      "high": 7.31,
      "low": 5.85,
      "close": 7.182,
      "volume": 625872.7,
      "turnover": 4174166.9066
    },
    {
      "time": 1760486400000,
      "open": 7.182,
      "high": 7.25,
      "low": 6.498,
      "close": 6.654,
      "volume": 369890.9,
      "turnover": 2530046.3006
    },
    {
      "time": 1760572800000,
      "open": 6.654,
      "high": 7.443,
      "low": 6.575,
      "close": 7.202,
      "volume": 446285.9,
      "turnover": 3182020.9266
    },
    {
      "time": 1760659200000,
      "open": 7.202,
      "high": 7.3,
      "low": 6.428,
      "close": 6.626,
      "volume": 292786.5,
      "turnover": 1996640.7064
    },
    {
      "time": 1760745600000,
      "open": 6.626,
      "high": 6.803,
      "low": 6.302,
      "close": 6.478,
      "volume": 110624.9,
      "turnover": 720074.6455
    },
    {
      "time": 1760832000000,
      "open": 6.478,
      "high": 6.644,
      "low": 6.352,
      "close": 6.472,
      "volume": 95333.6,
      "turnover": 619046.4777
    },
    {
      "time": 1760918400000,
      "open": 6.472,
      "high": 6.839,
      "low": 6.393,
      "close": 6.535,
      "volume": 79251.0,
      "turnover": 520745.3478
    },
    {
      "time": 1761004800000,
      "open": 6.535,
      "high": 7.133,
      "low": 6.227,
      "close": 6.583,
      "volume": 234153.3,
      "turnover": 1566305.5111
    },
    {
      "time": 1761091200000,
      "open": 6.583,
      "high": 6.716,
      "low": 6.433,
      "close": 6.531,
      "volume": 150771.2,
      "turnover": 990588.2415
    },
    {
      "time": 1761177600000,
      "open": 6.531,
      "high": 6.555,
      "low": 6.292,
      "close": 6.382,
      "volume": 72918.0,
      "turnover": 467637.087
    },
    {
      "time": 1761264000000,
      "open": 6.382,
      "high": 6.796,
      "low": 6.118,
      "close": 6.705,
      "volume": 106799.5,
      "turnover": 686667.9394
    },
    {
      "time": 1761350400000,
      "open": 6.705,
      "high": 6.717,
      "low": 6.49,
      "close": 6.568,
      "volume": 30874.7,
      "turnover": 203309.8535
    },
    {
      "time": 1761436800000,
      "open": 6.568,
      "high": 6.811,
      "low": 6.397,
      "close": 6.753,
      "volume": 32468.3,
      "turnover": 216352.0318
    },
    {
      "time": 1761523200000,
      "open": 6.753,
      "high": 7.541,
      "low": 6.686,
      "close": 6.868,
      "volume": 187818.3,
      "turnover": 1349769.4638
    },
    {
      "time": 1761609600000,
      "open": 6.868,
      "high": 6.893,
      "low": 6.456,
      "close": 6.588,
      "volume": 71297.2,
      "turnover": 477260.6437
    },
    {
      "time": 1761696000000,
      "open": 6.588,
      "high": 6.705,
      "low": 6.435,
      "close": 6.561,
      "volume": 70140.2,
      "turnover": 459513.7945
    },
    {
      "time": 1761782400000,
      "open": 6.561,
      "high": 6.689,
      "low": 6.526,
      "close": 6.671,
      "volume": 3380.1,
      "turnover": 22384.605
    }
  ],
  "count": 463,
  "last_update": "2025-10-30T03:49:16.098710",
  "rsi_last_candle": 43.76
}